Workbook

Sheet 1_Overview
A1: Pillar 1 Comprehensive Capability Mapping - v14.0 (FINAL)
A2: 199 strategic sub-capabilities · 22 tabs · ~6,200 rows · 6-batch build journey · 56 of 56 QA gates passed · Interactive Zennify-themed toggle cascade
A4: 1 - HOW TO USE THIS WORKBOOK
A5: Action | C5: How
A6: Quick start | B6: Open 17_Toggle_Control_Panel for the live cascade dashboard. Toggle any sub-cap in 2_Capability_Map column M (Zennify_Status) and watch dependent rows grey out across the workbook.
A7: Trace a capability | B7: Start at 2_Capability_Map. Pick a Sub_Cap_ID (e.g. P1C1.5.4). Filter every other tab by that ID - stories, L4 features, maturity, offerings, cross-pillar evidence are all keyed off it.
A8: Understand offerings | B8: Read 10_Productized_Offerings for offering catalog. Read 12_Offering_SubCap_Matrix for which sub-caps each offering addresses, with customized rationale + maturity lift per pair.
A9: Understand data products | B9: Read 11_Data_Products for the 36-module catalog across 7 categories. Read 13_DataProduct_SubCap_Matrix for direct sub-cap mappings.
A10: Find cross-pillar evidence | B10: Read 14_CrossPillar_Stories (742 stories from P2/P3/P4 with theme-derived P1 matches). Read 15_Theme_SubCap_Mapping for the theme-to-subcap rationale. Read 16_SubCap_CrossPillar_Coverage for per-sub-cap aggregate.
A11: Validate completeness | B11: Read 18_SubCap_Completeness_Profile for per-sub-cap completeness narrative. Read 19_Toggle_Cascade_Simulation for impact analysis. Read 20_Final_QA_Report for verification verdict across all 6 batches.
A12: Excel version requirement | B12: Excel 2021 or Excel 365 (XLOOKUP support). Workbook is set to fullCalcOnLoad so the toggle cascade evaluates the moment the file opens.
A14: 2 - ID SYSTEM (the keys that connect tabs)
A15: ID | B15: Format / Example | C15: What it identifies | D15: Tabs where it appears
A16: Sub_Cap_ID | B16: P1C{cat}.{l1}.{n} (e.g. P1C1.5.4) | C16: The MASTER KEY of the entire workbook. 199 unique IDs covering 4 categories (P1C1=Strategy & Vision; P1C2=Governance & Risk; P1C3=Innovation; P1C4=Change & Adoption). Sub-vertical variants use BK1/WM1/IC1/CU1/CL1/IB1 suffixes. | D16: 2_Capability_Map (col C); 3_User_Stories (col D); 5_L4 (col A); 6_Maturity (col A); 12 (col C); 13 (col C); 15 (col B as P1_Sub_Cap_ID); 16 (col A); 18 (col A); 19 (col A)
A17: Story_Key | B17: GEN-P1C{...}-M{X}-{NN} or JIRA-{key} | C17: Unique identifier for each user story. 1,302 P1-native stories in tab 3 plus 742 cross-pillar stories in tab 14 (originating in P2/P3/P4 but theme-matched to P1). | D17: 3_User_Stories (col A); 14_CrossPillar_Stories (col A)
A18: L3_ID | B18: L3-{vendor}-{platform} (e.g. L3-DB-LAKEHOUSE, L3-SF-FSC) | C18: 45 platform IDs covering Salesforce + Databricks + MuleSoft + nCino + Twilio. Each L3 is a distinct technology platform a sub-cap can be addressed by. | D18: 4_L3_Detailed (col A); 5_L4_Detailed (col C); 10_Productized_Offerings (col L: L3_Platforms_Used)
A19: Offering_ID | B19: OFF-{shortname} (e.g. OFF-DATA-MOD, OFF-FSC-PLATFORM) | C19: 13 offering IDs (9 priority + 4 supporting). Modern Managed Services is the wrap-around offering. | D19: 10_Productized_Offerings (col A); 12_Offering_SubCap_Matrix (col A)
A20: Module_ID | B20: DP-{cat}.{n} (e.g. DP-1.1, DP-7.3) | C20: 36 data product module IDs across 7 categories (Identity & Golden Record, Risk & Intelligence, Integration & Connectivity, Content & Document Intelligence, Journey & Engagement, Analytics & Insights, Governance & Quality). | D20: 11_Data_Products (col A); 13_DataProduct_SubCap_Matrix (col A)
A21: Theme | B21: 8 themes: governance, compliance_regulatory, strategy, data_governance, culture_change, kpi, innovation, risk | C21: Cross-pillar evidence themes. Each theme maps to 3-5 P1 sub-caps with customized rationale. | D21: 14_CrossPillar_Stories (col G: P1_Themes); 15_Theme_SubCap_Mapping (col A)
A22: Use_Case_ID | B22: UC-{archetype}-{n} | C22: 906 use cases organized into 22 archetypes. Each L4 feature is keyed to specific use case IDs. | D22: 5_L4_Detailed (col L: Use_Case_IDs_Using_Feature); 2_Capability_Map (col K: Use_Cases)
A23: Agent_ID / Construct_ID | B23: AGT-* / CON-* | C23: Agentforce agents (130) and validated platform constructs (37). Constructs are the anti-fabrication anchor - only catalog references that have been verified against vendor docs. | D23: 8_Agentforce_Agents_List; 9_Platform_Constructs_Library
A24: Zennify_Status | B24: Active / Inactive (toggle) | C24: The activation flag for each sub-cap. Default Active. Toggling drives the entire cascade across 9 dependent tabs + 2 aggregate tabs. | D24: 2_Capability_Map (col M, source); Effective_Status columns in tabs 3, 5, 6, 12, 13, 14, 15, 16, 18, 19; aggregate health columns in 10, 11; live counters in 17
A26: 3 - TAB INVENTORY (what each tab is, primary content, primary key)
A27: Tab | B27: What it is / what it stands for | C27: Content & primary keys | D27: Rows × Cols
A28: 1_Overview | B28: THIS TAB - navigation reference and how-to guide. | C28: Workbook orientation: ID system, tab inventory, linkage map, toggle system, batch journey summary. No data keys. | D28: 76 × 4
A29: 2_Capability_Map | B29: THE CANONICAL CAPABILITY DEFINITION. Source of truth for the 199 P1 sub-caps. Source of the toggle cascade. | C29: PRIMARY KEY: Sub_Cap_ID (col C). Other cols: Category (P1C1-P1C4), L1_Capability, Description, Solution_Type, Tier, Personas, L3 platforms addressing, L4 features available, Use Cases, Story refs, Zennify_Status (toggle, col M). | D29: 199 × 13
A30: 3_User_Stories_Catalogue | B30: P1-NATIVE USER STORIES. Stories specifically written for P1 capabilities. | C30: PRIMARY KEY: Story_Key (col A). Joins to: Sub_Cap_ID (col D). Other: Source_Type, Source_Ref, Use_Case_IDs, L4_Features_Used, Match_Confidence, Story_Summary, W/X/Y (Description/AC/SD), Implementation Steps, Deployment Checklist, Jira_Project_URL, Zennify_Effective_Status (cascade). | D30: 1,302 × 16
A31: 4_L3_Detailed | B31: PLATFORM CATALOG. The 45 L3 technology platforms used to address sub-caps. | C31: PRIMARY KEY: L3_ID (col A). Joins to: Sub_Cap_ID (col M: Linked_Sub_Caps_Top5). Other: Vendor, Platform_Name, Description, Detailed_Capabilities, Setup_Path, Prerequisites, Customization_Extension_Points, Common_Combinations, Linked_L4_Features, Reference_URL, Source_Evidence, Use_When. | D31: 45 × 16
A32: 5_L4_Detailed_Features | B32: L4 FEATURES (per sub-cap × use case). The most granular vendor-feature catalog. | C32: PRIMARY KEY: composite (Sub_Cap_ID + L3_Platform_ID + Feature_Name). Joins: Sub_Cap_ID (col A), L3_Platform_ID (col C), Use_Case_IDs_Using_Feature (col L). Other: Customization_Level, Detailed_Description, Configuration_Path, Validated_Customization_Patterns, Story_Refs_Using_Feature, Reference_URL, Is_Supplemental, Zennify_Effective_Status. | D32: 3,129 × 16
A33: 6_Maturity_Descriptors | B33: M1–M5 MATURITY PROGRESSION per sub-cap. | C33: PRIMARY KEY: Sub_Cap_ID (col A). Other: Category, L1_Capability, M1_Foundational, M1_Foundational_Features, M2_Developing, M2_Developing_Features, M3_Established_AI_Assisted, M3_Agentic_Features, M4_Advanced_Hybrid_Agentic, M4_Cross_System_Orchestration, M5_Transformational_Headless360, M5_Headless_360_Surfaces, Zennify_Effective_Status. | D33: 199 × 15
A34: 7_Product_Catalogue | B34: VENDOR COMPONENT CATALOG. 311 vendor products across the supporting ecosystem. | C34: Primary keys: Vendor + Product_Name. Used as cross-reference for L4 features and L3 platforms. No cascade column (this is a vendor reference, not sub-cap-keyed). | D34: 311 × 11
A35: 8_Agentforce_Agents_List | B35: AGENTFORCE AGENTS. 130 agents (Salesforce official + retail-bank library). | C35: Primary key: Agent_ID. Each agent has URL, persona, sub-vertical fit, and use case fit. | D35: 130 × 9
A36: 9_Platform_Constructs_Library | B36: VALIDATED PLATFORM CONSTRUCTS. The anti-fabrication anchor. | C36: Primary key: Construct_ID. Only contains constructs verified against vendor public docs - used to prevent hallucinated capability claims elsewhere in the catalog. | D36: 37 × 5
A37: 10_Productized_Offerings | B37: OFFERING CATALOG (BATCH 3). 13 offerings: 9 priority + 4 supporting; OFF-MMS is the wrap-around. | C37: PRIMARY KEY: Offering_ID (col A). Joins to: Sub_Cap_ID via tab 12 (Offering_SubCap_Matrix). Other: Category, Wrap_Around, Status, Overview, Industry_Challenge, Outcomes, Core_Capabilities, Tiers, Primary_Vendors, L3_Platforms_Used, Target_Personas, Reference_URL, Source_Evidence, Source_Doc_Section. Aggregate cascade columns: Total_Mapped_SubCaps, Active_Mapped_SubCaps, Linkage_Health_Pct (red→yellow→green color scale), Zennify_Effective_Status (Active/Partial/Inactive). | D37: 13 × 20
A38: 11_Data_Products | B38: DATA PRODUCT MODULE CATALOG (BATCH 3). 36 modules across 7 categories. | C38: PRIMARY KEY: Module_ID (col A) e.g. DP-1.1, DP-7.3. Joins via tab 13. Other: Category, Module_Name, Description, Typical_Pairing (Offerings), Validation_Strength, Reference_URL, Source_Doc_Section. Aggregate cascade: Total_Mapped, Active_Mapped, Linkage_Health_Pct, Effective_Status (with "No-Direct-Map" 4th state for modules without direct sub-cap mapping). | D38: 36 × 12
... A49: Z2_Plan_Revisions | B49: PLAN REVISIONS LOG across all 6 batches. | C49: 40 rows: each revision documents what changed, why (often citing user feedback), and forward-looking notes for future iterations. | D49: 40 × 5
A51: 4 - TAB LINKAGE MAP (which IDs connect which tabs)
A52: From tab | B52: Via key (and column) | C52: To tab | D52: Linkage purpose
A53: 2_Capability_Map | B53: Sub_Cap_ID (col C) | C53: 3_User_Stories_Catalogue (col D) | D53: Find all P1-native stories for a sub-cap
A54: 2_Capability_Map | B54: Sub_Cap_ID (col C) | C54: 5_L4_Detailed_Features (col A) | D54: Find all L4 features delivering a sub-cap (per use case)
A55: 2_Capability_Map | B55: Sub_Cap_ID (col C) | C55: 6_Maturity_Descriptors (col A) | D55: Find M1-M5 progression for a sub-cap
A56: 2_Capability_Map | B56: Sub_Cap_ID (col C) | C56: 12_Offering_SubCap_Matrix (col C) | D56: Find which offerings address a sub-cap (with rationale)
A57: 2_Capability_Map | B57: Sub_Cap_ID (col C) | C57: 13_DataProduct_SubCap_Matrix (col C) | D57: Find which data product modules deliver a sub-cap
A58: 2_Capability_Map | B58: Sub_Cap_ID (col C) | C58: 15_Theme_SubCap_Mapping (col B as P1_Sub_Cap_ID) | D58: Find theme that classifies a sub-cap for cross-pillar evidence
A59: 2_Capability_Map | B59: Sub_Cap_ID (col C) | C59: 16_SubCap_CrossPillar_Coverage (col A) | D59: Aggregate cross-pillar evidence count for a sub-cap
A60: 2_Capability_Map | B60: Sub_Cap_ID (col C) | C60: 18_SubCap_Completeness_Profile (col A) | D60: Per-sub-cap completeness narrative
A61: 2_Capability_Map | B61: Sub_Cap_ID (col C) | C61: 19_Toggle_Cascade_Simulation (col A) | D61: Per-sub-cap toggle impact
A62: 2_Capability_Map (col M Zennify_Status) | B62: XLOOKUP cascade | C62: All cascade tabs (3, 5, 6, 12, 13, 14, 15, 16, 18, 19) | D62: Active/Inactive toggle propagates to dependent rows. Source col M is the only writable status; all dependents are read-only XLOOKUP formulas.
A63: 17_Toggle_Control_Panel | B63: COUNTIF live formulas | C63: All cascade tabs | D63: Real-time aggregate state of the entire workbook
... A75: 3_User_Stories_Catalogue | B75: Use_Case_IDs (col F) | C75: 5_L4_Detailed_Features (col L) | D75: Find use cases addressed by a story
A77: 5 - TOGGLE CASCADE SYSTEM (interactive control)
A78: Layer | B78: Tabs | C78: Behavior on Inactive
A79: SOURCE | B79: 2_Capability_Map (col M) | C79: Toggle each of 199 sub-caps Active / Inactive via dropdown. Cell turns Zennify Teal (Active) or grey strikethrough (Inactive). The whole row greys out when Inactive.
A80: DIRECT CASCADE (2-state) | B80: Tabs 3, 5, 6, 12, 13, 15, 16, 18, 19 | C80: Each row has a Zennify_Effective_Status column with XLOOKUP into 2_Capability_Map.Sub_Cap_ID → Zennify_Status. Default returns "Active". When source is Inactive, the row greys out.
A81: MULTI-MAPPED CASCADE (3-state) | B81: Tab 14 (Cross-Pillar Stories) | C81: Each row has linked sub-caps array. SUMPRODUCT counts active linked sub-caps. Status: Active (all linked active), Partial (some active - light orange tint), Inactive (none active).
A82: AGGREGATE CASCADE (3-state) | B82: Tabs 10 (Offerings), 11 (Data Products) | C82: COUNTIFS aggregates over the cascade columns in tabs 12 and 13. Total_Mapped + Active_Mapped + Linkage_Health_Pct (red → yellow → green color scale) + Effective_Status. Tab 11 has 4th state "No-Direct-Map" for modules without direct mappings.
A83: LIVE DASHBOARD | B83: Tab 17 (Toggle Control Panel) | C83: COUNTIF formulas show real-time counts of active/inactive across the entire workbook. Includes coverage % and design notes about Excel version requirement (2021+/365 for XLOOKUP).
A85: 6 - BUILD JOURNEY (6-batch evolution to v14.0)
A86: Batch | B86: Focus | C86: Deliverable / new tabs | D86: Status
A87: Batch 1 | B87: Foundation QA + URL validation + ESG decision | C87: No new tabs (foundation cleanup); story keys + Jira links validated; ESG sub-caps integrated | D87: COMPLETE
A88: Batch 2 (Final v2) | B88: L3/L4 refactor + customization classifier + Headless 360 | C88: + 4 tabs: 4_L3_Detailed (45), 5_L4_Detailed (3,129), 8_Agentforce (130), 9_Constructs (37); 199 sub-caps with full L3/L4 detail; 22 archetypes × 209 keywords; Solution_Type classifier | D88: COMPLETE
A89: Batch 3 | B89: Productized Offerings + Data Products + Strict Mappings | C89: + 4 tabs: 10_Offerings (13), 11_Data_Products (36), 12_Offering_SubCap_Matrix (68), 13_DP_SubCap_Matrix (29); customized rationale + maturity lift per pair | D89: COMPLETE
A90: Batch 4 | B90: Cross-Pillar Story Integration with Offering Linkage | C90: + 3 tabs: 14_CrossPillar_Stories (742), 15_Theme_SubCap (33), 16_Coverage (33); 742 P2/P3/P4 stories with theme-derived P1 matches and transitive offering linkage | D90: COMPLETE
A91: Batch 5 | B91: Zennify Active/Inactive Toggle XLOOKUP Cascade | C91: + 1 tab: 17_Toggle_Control_Panel; cascade columns added to 9 tabs; 3-state semantics; aggregate health for offerings/data products | D91: COMPLETE
A92: Batch 6 (FINAL) | B92: Knowledge Graph Validation + v14.0 Distribution | C92: + 3 tabs: 18_Completeness_Profile (199 unique narratives), 19_Cascade_Simulation (199 rows), 20_Final_QA_Report (7 sections); zero orphan refs; 100% core coverage; 56 of 56 QA gates PASS | D92: COMPLETE
A94: 7 - FINAL QA STATUS (full report in tab 20)
A95: Dimension | B95: Result | C95: Where to verify
A96: Knowledge graph core completeness | B96: 199/199 sub-caps with all 5 dimensions (stories, L4, maturity, L3, use cases) | C96: Tab 20 §1; Tab 18 (per-sub-cap profile)
A97: Reference integrity | B97: Zero orphan references across 1,302 stories + 3,129 L4 + 68 + 29 mappings | C97: Tab 20 §2
A98: Customization integrity | B98: 199 unique narratives + 68 + 29 + 33 unique mapping rationales - no template reuse | C98: Tab 20 §3
A99: URL / source-evidence coverage | B99: 146 of 146 public-facing entries have reference URL | C99: Tab 20 §4
A100: Toggle cascade integrity | B100: Verified end-to-end; calc-on-load forced; mathematically validated | C100: Tab 20 §5; Tab 17 (live dashboard); Tab 19 (simulation)
A101: QA gates across 6 batches | B101: 56 of 56 PASS (zero failures) | C101: Z1_QA_Gates (cumulative log)
A102: Excel version | B102: Excel 2021 / 365 required (XLOOKUP) | C102: Tab 17 design notes
A103: Final verdict | B103: COMPLETE - ready for distribution | C103: Tab 20 §7
A105: v14.0 FINAL - Open 17_Toggle_Control_Panel for the live dashboard, then 2_Capability_Map column M to start exercising the cascade.
A107: VALUE CHAIN REFERENCE
A108: Companion Value Chain Reference Document | B108: 10 subverticals × 8 universal MECE clusters × 130 customized stages, each with full P1+P2+P3+P4 lens. Used as the value-chain anchor for tab 21_VC_Mapping_PerSubcap. Each subcap is mapped to one or more stages of each subvertical's value chain.
A109: Google Sheets URL | B109: https://docs.google.com/spreadsheets/d/1Rxkr9fhIP3NF_jqEOWllqSFbwymZYmb5g_Vr7-SPaes/edit?gid=428430531#gid=428430531

Sheet 2_Capability_Map
A1: Category | B1: L1_Capability | C1: Sub_Cap_ID | D1: Sub_Cap_Name | E1: Description | F1: Solution_Type | G1: Tier | H1: Personas | I1: L3_Platforms_Addressing_SubCap | J1: L4_Features_Available | K1: Use_Cases | L1: Story_Refs_with_UC_Links | M1: Zennify_Status
A2: P1C1 | B2: Strategy Foundation & Alignment | C2: P1C1.1.1 | D2: Digital Strategy Document | E2: Documented digital transformation strategy with clear objectives, scope, and success criteria | F2: Hybrid | G2: T1 | H2: CIO, CDO, Chief Strategy Officer, Strategy & Planning Lead | I2: [L3-TBL-EMBED] Tableau Embedded Analytics (count: 5) [L3-SF-AGENTIC-SEARCH] Agentic Enterprise Search (count: 3) [L3-SF-AGENTFORCE] Salesforce Agentforce (count: 2) | J2: Agentforce Builder [L3: L3-SF-AGENTFORCE, Salesforce, Low-Code] Agentforce Topics & Actions [L3: L3-SF-AGENTFORCE, Salesforce, Configuration] Agentic Enterprise Search Engine [L3: L3-SF-AGENTIC-SEARCH, Salesforce, Configuration] Citations & Provenance Engine [L3: L3-SF-AGENTIC-SEARCH, Salesforce, Configuration] Search Skill in Agentforce [L3: L3-SF-AGENTIC-SEARCH, Salesforce, Configuration] Tableau Embedding API v3 [L3: L3-TBL-EMBED, Tableau, Code] VizQL Data Service (Headless Data API) [L3: L3-TBL-EMBED, Tableau, API] External Authorization Servers (EAS) [L3: L3-TBL-EMBED, Tableau, Configuration] Domain Allowlist for Embedding [L3: L3-TBL-EMBED, Tableau, Configuration] Unified Access Tokens (UATs) [L3: L3-TBL-EMBED, Tableau, Configuration] | K2: P1C1.1.1.UC1 [AI_AUTHOR]: AI-assisted authoring & maintenance of Digital Strategy Document P1C1.1.1.UC2 [WORKFLOW_CADENCE]: Workflow-orchestrated review & refresh cycle for Digital Strategy Document P1C1.1.1.UC3 [EXEC_DASHBOARD]: Real-time executive performance dashboard for Digital Strategy Document P1C1.1.1.UC4 [STAKEHOLDER_COMM]: Multi-channel stakeholder communication of Digital Strategy Document P1C1.1.1.UC5 [BOARD_PACK]: Automated board-pack assembly for Digital Strategy Document | L2: JIRA-BCFSC-1273 [src: jira_completed] → UCs: P1C1.1.1.UC2, P1C1.1.1.UC1 JIRA-BCFSC-1274 [src: jira_completed] → UCs: P1C1.1.1.UC2 JIRA-EBT-277 [src: jira_completed] → UCs: P1C1.1.1.UC2, P1C1.1.1.UC1 JIRA-EBT-378 [src: jira_completed] → UCs: P1C1.1.1.UC1, P1C1.1.1.UC3 JIRA-FFBI-760 [src: jira_completed] → UCs: P1C1.1.1.UC2 JIRA-IMA-223 [src: jira_completed] → UCs: P1C1.1.1.UC1 JIRA-MCUDA-13 [src: jira_completed] → UCs: P1C1.1.1.UC3 JIRA-MF-1073 [src: jira_completed] → UCs: P1C1.1.1.UC2, P1C1.1.1.UC1 JIRA-MF-1107 [src: jira_completed] → UCs: P1C1.1.1.UC2 JIRA-MF-235 [src: jira_completed] → UCs: P1C1.1.1.UC1 JIRA-MF-283 [src: jira_completed] → UCs: P1C1.1.1.UC1 JIRA-MF-288 [src: jira_completed] → UCs: P1C1.1.1.UC5 JIRA-MF-289 [src: jira_completed] → UCs: P1C1.1.1.UC1 JIRA-MF-290 [src: jira_completed] → UCs: P1C1.1.1.UC5 JIRA-MF-291 [src: jira_completed] → UCs: P1C1.1.1.UC2 JIRA-MF-294 [src: jira_completed] → UCs: P1C1.1.1.UC5 JIRA-MF-295 [src: jira_completed] → UCs: P1C1.1.1.UC1 JIRA-MF-324 [src: jira_completed] → UCs: P1C1.1.1.UC5, P1C1.1.1.UC1 JIRA-MF-325 [src: jira_completed] → UCs: P1C1.1.1.UC5, P1C1.1.1.UC1 JIRA-MF-670 [src: jira_completed] → UCs: P1C1.1.1.UC2 JIRA-NWFCU-274 [src: jira_completed] → UCs: P1C1.1.1.UC1, P1C1.1.1.UC3 JIRA-PF-501 [src: jira_completed] → UCs: P1C1.1.1.UC2 JIRA-PF-59 [src: jira_completed] → UCs: P1C1.1.1.UC2 JIRA-ZENN2-125 [src: jira_completed] → UCs: P1C1.1.1.UC2 JIRA-ZENN2-90 [src: jira_completed] → UCs: P1C1.1.1.UC1 | M2: Active
A3: P1C1 | B3: Strategy Foundation & Alignment | C3: P1C1.1.2 | D3: Business Alignment | E3: Alignment of digital strategy with overall business strategy and objectives | F3: Hybrid | G3: T1 | H3: CIO, CDO, Chief Strategy Officer, Strategy & Planning Lead | I3: [L3-TBL-EMBED] Tableau Embedded Analytics (count: 5) [L3-SF-AGENTIC-SEARCH] Agentic Enterprise Search (count: 3) [L3-SF-AGENTFORCE] Salesforce Agentforce (count: 2) | J3: Agentforce Builder [L3: L3-SF-AGENTFORCE, Salesforce, Low-Code] Agentforce Topics & Actions [L3: L3-SF-AGENTFORCE, Salesforce, Configuration] Agentic Enterprise Search Engine [L3: L3-SF-AGENTIC-SEARCH, Salesforce, Configuration] Citations & Provenance Engine [L3: L3-SF-AGENTIC-SEARCH, Salesforce, Configuration] Search Skill in Agentforce [L3: L3-SF-AGENTIC-SEARCH, Salesforce, Configuration] Tableau Embedding API v3 [L3: L3-TBL-EMBED, Tableau, Code] VizQL Data Service (Headless Data API) [L3: L3-TBL-EMBED, Tableau, API] External Authorization Servers (EAS) [L3: L3-TBL-EMBED, Tableau, Configuration] Domain Allowlist for Embedding [L3: L3-TBL-EMBED, Tableau, Configuration] Unified Access Tokens (UATs) [L3: L3-TBL-EMBED, Tableau, Configuration] | K3: P1C1.1.2.UC5 [BOARD_PACK]: Automated board-pack assembly for Business Alignment P1C1.1.2.UC3 [EXEC_DASHBOARD]: Real-time executive performance dashboard for Business Alignment P1C1.1.2.UC4 [STAKEHOLDER_COMM]: Multi-channel stakeholder communication of Business Alignment P1C1.1.2.UC1 [AI_AUTHOR]: AI-assisted authoring & maintenance of Business Alignment P1C1.1.2.UC2 [WORKFLOW_CADENCE]: Workflow-orchestrated review & refresh cycle for Business Alignment | L3: JIRA-MCUDA-13 [src: jira_completed] → UCs: P1C1.1.2.UC3 JIRA-ZENN2-125 [src: jira_completed] → UCs: P1C1.1.2.UC5 | M3: Active
A4: P1C1 | B4: Strategy Foundation & Alignment | C4: P1C1.1.3 | D4: Strategy Refresh Cadence | E4: Regular review and update cycle for digital strategy (annual minimum) | F4: Hybrid | G4: T1 | H4: CIO, CDO, Chief Strategy Officer, Strategy & Planning Lead | I4: [L3-TBL-EMBED] Tableau Embedded Analytics (count: 5) [L3-SF-AGENTIC-SEARCH] Agentic Enterprise Search (count: 3) [L3-SF-AGENTFORCE] Salesforce Agentforce (count: 2) | J4: Agentforce Builder [L3: L3-SF-AGENTFORCE, Salesforce, Low-Code] Agentforce Topics & Actions [L3: L3-SF-AGENTFORCE, Salesforce, Configuration] Agentic Enterprise Search Engine [L3: L3-SF-AGENTIC-SEARCH, Salesforce, Configuration] Citations & Provenance Engine [L3: L3-SF-AGENTIC-SEARCH, Salesforce, Configuration] Search Skill in Agentforce [L3: L3-SF-AGENTIC-SEARCH, Salesforce, Configuration] Tableau Embedding API v3 [L3: L3-TBL-EMBED, Tableau, Code] VizQL Data Service (Headless Data API) [L3: L3-TBL-EMBED, Tableau, API] External Authorization Servers (EAS) [L3: L3-TBL-EMBED, Tableau, Configuration] Domain Allowlist for Embedding [L3: L3-TBL-EMBED, Tableau, Configuration] Unified Access Tokens (UATs) [L3: L3-TBL-EMBED, Tableau, Configuration] | K4: P1C1.1.3.UC5 [BOARD_PACK]: Automated board-pack assembly for Strategy Refresh Cadence P1C1.1.3.UC3 [EXEC_DASHBOARD]: Real-time executive performance dashboard for Strategy Refresh Cadence P1C1.1.3.UC4 [STAKEHOLDER_COMM]: Multi-channel stakeholder communication of Strategy Refresh Cadence P1C1.1.3.UC1 [AI_AUTHOR]: AI-assisted authoring & maintenance of Strategy Refresh Cadence P1C1.1.3.UC2 [WORKFLOW_CADENCE]: Workflow-orchestrated review & refresh cycle for Strategy Refresh Cadence | L4: JIRA-IAMC-18 [src: jira_completed] → UCs: P1C1.1.3.UC5 | M4: Active
A5: P1C1 | B5: Strategy Foundation & Alignment | C5: P1C1.1.4 | D5: Vision Communication | E5: Clear communication of digital vision across all organizational levels | F5: Traditional | G5: T1 | H5: CIO, CDO, Chief Strategy Officer, Strategy & Planning Lead | I5: [L3-TBL-EMBED] Tableau Embedded Analytics (count: 5) [L3-SF-AGENTIC-SEARCH] Agentic Enterprise Search (count: 3) [L3-SF-AGENTFORCE] Salesforce Agentforce (count: 2) | J5: Agentforce Builder [L3: L3-SF-AGENTFORCE, Salesforce, Low-Code] Agentforce Topics & Actions [L3: L3-SF-AGENTFORCE, Salesforce, Configuration] Agentic Enterprise Search Engine [L3: L3-SF-AGENTIC-SEARCH, Salesforce, Configuration] Citations & Provenance Engine [L3: L3-SF-AGENTIC-SEARCH, Salesforce, Configuration] Search Skill in Agentforce [L3: L3-SF-AGENTIC-SEARCH, Salesforce, Configuration] Tableau Embedding API v3 [L3: L3-TBL-EMBED, Tableau, Code] VizQL Data Service (Headless Data API) [L3: L3-TBL-EMBED, Tableau, API] External Authorization Servers (EAS) [L3: L3-TBL-EMBED, Tableau, Configuration] Domain Allowlist for Embedding [L3: L3-TBL-EMBED, Tableau, Configuration] Unified Access Tokens (UATs) [L3: L3-TBL-EMBED, Tableau, Configuration] | K5: P1C1.1.4.UC4 [STAKEHOLDER_COMM]: Multi-channel stakeholder communication of Vision Communication P1C1.1.4.UC3 [EXEC_DASHBOARD]: Real-time executive performance dashboard for Vision Communication P1C1.1.4.UC5 [BOARD_PACK]: Automated board-pack assembly for Vision Communication P1C1.1.4.UC1 [AI_AUTHOR]: AI-assisted authoring & maintenance of Vision Communication P1C1.1.4.UC2 [WORKFLOW_CADENCE]: Workflow-orchestrated review & refresh cycle for Vision Communication | L5: JIRA-BB-475 [src: jira_completed] → UCs: P1C1.1.4.UC4 | M5: Active
A6: P1C1 | B6: Strategy Foundation & Alignment | C6: P1C1.1.5 | D6: Board Engagement | E6: Regular board-level engagement and reporting on digital strategy progress | F6: Traditional | G6: T1 | H6: CIO, CDO, Chief Strategy Officer, Strategy & Planning Lead | I6: [L3-TBL-EMBED] Tableau Embedded Analytics (count: 5) [L3-SF-AGENTIC-SEARCH] Agentic Enterprise Search (count: 3) [L3-SF-AGENTFORCE] Salesforce Agentforce (count: 2) | J6: Agentforce Builder [L3: L3-SF-AGENTFORCE, Salesforce, Low-Code] Agentforce Topics & Actions [L3: L3-SF-AGENTFORCE, Salesforce, Configuration] Agentic Enterprise Search Engine [L3: L3-SF-AGENTIC-SEARCH, Salesforce, Configuration] Citations & Provenance Engine [L3: L3-SF-AGENTIC-SEARCH, Salesforce, Configuration] Search Skill in Agentforce [L3: L3-SF-AGENTIC-SEARCH, Salesforce, Configuration] Tableau Embedding API v3 [L3: L3-TBL-EMBED, Tableau, Code] VizQL Data Service (Headless Data API) [L3: L3-TBL-EMBED, Tableau, API] External Authorization Servers (EAS) [L3: L3-TBL-EMBED, Tableau, Configuration] Domain Allowlist for Embedding [L3: L3-TBL-EMBED, Tableau, Configuration] Unified Access Tokens (UATs) [L3: L3-TBL-EMBED, Tableau, Configuration] | K6: P1C1.1.5.UC1 [AI_AUTHOR]: AI-assisted authoring & maintenance of Board Engagement P1C1.1.5.UC2 [WORKFLOW_CADENCE]: Workflow-orchestrated review & refresh cycle for Board Engagement P1C1.1.5.UC3 [EXEC_DASHBOARD]: Real-time executive performance dashboard for Board Engagement P1C1.1.5.UC4 [STAKEHOLDER_COMM]: Multi-channel stakeholder communication of Board Engagement P1C1.1.5.UC5 [BOARD_PACK]: Automated board-pack assembly for Board Engagement | L6: JIRA-FFBI-497 [src: jira_completed] → UCs: P1C1.1.5.UC1 JIRA-FFBI-511 [src: jira_completed] → UCs: P1C1.1.5.UC1 JIRA-FFBI-526 [src: jira_completed] → UCs: P1C1.1.5.UC1 JIRA-FFBI-527 [src: jira_completed] → UCs: P1C1.1.5.UC1 JIRA-FFBI-534 [src: jira_completed] → UCs: P1C1.1.5.UC2 JIRA-FFBI-535 [src: jira_completed] → UCs: P1C1.1.5.UC1 JIRA-INVYT-251 [src: jira_completed] → UCs: P1C1.1.5.UC1 JIRA-INVYT-68 [src: jira_completed] → UCs: P1C1.1.5.UC1, P1C1.1.5.UC3 JIRA-NCM-113 [src: jira_completed] → UCs: P1C1.1.5.UC1 JIRA-NWFCU-47 [src: jira_completed] → UCs: P1C1.1.5.UC2 JIRA-PF-652 [src: jira_completed] → UCs: P1C1.1.5.UC3, P1C1.1.5.UC1 JIRA-SILVERGATE-253 [src: jira_completed] → UCs: P1C1.1.5.UC1 JIRA-SILVERGATE-264 [src: jira_completed] → UCs: P1C1.1.5.UC3 JIRA-STLS-16 [src: jira_completed] → UCs: P1C1.1.5.UC3, P1C1.1.5.UC1 JIRA-STLS-179 [src: jira_completed] → UCs: P1C1.1.5.UC3 JIRA-STLS-180 [src: jira_completed] → UCs: P1C1.1.5.UC1 JIRA-STLS-181 [src: jira_completed] → UCs: P1C1.1.5.UC3 JIRA-STLS-193 [src: jira_completed] → UCs: P1C1.1.5.UC1 JIRA-STLS-79 [src: jira_completed] → UCs: P1C1.1.5.UC1 JIRA-STLS-81 [src: jira_completed] → UCs: P1C1.1.5.UC2 JIRA-STLS-84 [src: jira_completed] → UCs: P1C1.1.5.UC2 JIRA-STLS-85 [src: jira_completed] → UCs: P1C1.1.5.UC2 JIRA-STLS-86 [src: jira_completed] → UCs: P1C1.1.5.UC2 JIRA-STLS-87 [src: jira_completed] → UCs: P1C1.1.5.UC2 JIRA-ZENN2-88 [src: jira_completed] → UCs: P1C1.1.5.UC1 | M6: Active
A7: P1C1 | B7: Roadmap & Planning | C7: P1C1.2.1 | D7: Multi-Year Roadmap | E7: Documented 3-5 year digital transformation roadmap with milestones | F7: Hybrid | G7: T1 | H7: CIO, Program Director, Portfolio Manager, Architecture Lead | I7: [L3-TBL-EMBED] Tableau Embedded Analytics (count: 6) [L3-SF-AGENTIC-SEARCH] Agentic Enterprise Search (count: 4) [L3-SF-AGENTFORCE] Salesforce Agentforce (count: 2) | J7: Agentforce Builder [L3: L3-SF-AGENTFORCE, Salesforce, Low-Code] Agentforce Topics & Actions [L3: L3-SF-AGENTFORCE, Salesforce, Configuration] Agentic Enterprise Search Engine [L3: L3-SF-AGENTIC-SEARCH, Salesforce, Configuration] Federated Retrieval (Connected Sources) [L3: L3-SF-AGENTIC-SEARCH, Salesforce, API] Citations & Provenance Engine [L3: L3-SF-AGENTIC-SEARCH, Salesforce, Configuration] Search Skill in Agentforce [L3: L3-SF-AGENTIC-SEARCH, Salesforce, Configuration] Tableau Embedding API v3 [L3: L3-TBL-EMBED, Tableau, Code] Connected Apps with JWT Authentication [L3: L3-TBL-EMBED, Tableau, Configuration] VizQL Data Service (Headless Data API) [L3: L3-TBL-EMBED, Tableau, API] External Authorization Servers (EAS) [L3: L3-TBL-EMBED, Tableau, Configuration] Domain Allowlist for Embedding [L3: L3-TBL-EMBED, Tableau, Configuration] Unified Access Tokens (UATs) [L3: L3-TBL-EMBED, Tableau, Configuration] | K7: P1C1.2.1.UC2 [ALIGNMENT_LINK]: Strategy-to-execution linkage for Multi-Year Roadmap P1C1.2.1.UC4 [WORKFLOW_CADENCE]: Workflow-orchestrated review & refresh cycle for Multi-Year Roadmap P1C1.2.1.UC3 [EXEC_DASHBOARD]: Real-time executive performance dashboard for Multi-Year Roadmap P1C1.2.1.UC1 [AI_AUTHOR]: AI-assisted authoring & maintenance of Multi-Year Roadmap P1C1.2.1.UC5 [STAKEHOLDER_COMM]: Multi-channel stakeholder communication of Multi-Year Roadmap | L7: JIRA-BCFSC-1273 [src: jira_completed] → UCs: P1C1.2.1.UC4, P1C1.2.1.UC1 JIRA-BCFSC-1274 [src: jira_completed] → UCs: P1C1.2.1.UC4 JIRA-EBT-277 [src: jira_completed] → UCs: P1C1.2.1.UC4, P1C1.2.1.UC1 JIRA-EBT-378 [src: jira_completed] → UCs: P1C1.2.1.UC3, P1C1.2.1.UC1 JIRA-FFBI-760 [src: jira_completed] → UCs: P1C1.2.1.UC4 JIRA-IMA-223 [src: jira_completed] → UCs: P1C1.2.1.UC2 JIRA-MF-1073 [src: jira_completed] → UCs: P1C1.2.1.UC4, P1C1.2.1.UC1 JIRA-MF-1107 [src: jira_completed] → UCs: P1C1.2.1.UC4 JIRA-MF-235 [src: jira_completed] → UCs: P1C1.2.1.UC1 JIRA-MF-283 [src: jira_completed] → UCs: P1C1.2.1.UC4 JIRA-MF-288 [src: jira_completed] → UCs: P1C1.2.1.UC4 JIRA-MF-289 [src: jira_completed] → UCs: P1C1.2.1.UC4 JIRA-MF-290 [src: jira_completed] → UCs: P1C1.2.1.UC4 JIRA-MF-291 [src: jira_completed] → UCs: P1C1.2.1.UC4 JIRA-MF-294 [src: jira_completed] → UCs: P1C1.2.1.UC4 JIRA-MF-324 [src: jira_completed] → UCs: P1C1.2.1.UC1 JIRA-MF-325 [src: jira_completed] → UCs: P1C1.2.1.UC1 JIRA-MF-670 [src: jira_completed] → UCs: P1C1.2.1.UC4 JIRA-NWFCU-274 [src: jira_completed] → UCs: P1C1.2.1.UC3, P1C1.2.1.UC1 JIRA-PF-501 [src: jira_completed] → UCs: P1C1.2.1.UC4 JIRA-PF-504 [src: jira_completed] → UCs: P1C1.2.1.UC4 JIRA-PF-505 [src: jira_completed] → UCs: P1C1.2.1.UC2 JIRA-PF-508 [src: jira_completed] → UCs: P1C1.2.1.UC2 JIRA-PF-59 [src: jira_completed] → UCs: P1C1.2.1.UC2 JIRA-ZENN2-90 [src: jira_completed] → UCs: P1C1.2.1.UC2 | M7: Active
A8: P1C1 | B8: Roadmap & Planning | C8: P1C1.2.2 | D8: Initiative Prioritization | E8: Framework for prioritizing digital initiatives based on value and feasibility | F8: Hybrid | G8: T1 | H8: CIO, Program Director, Portfolio Manager, Architecture Lead | I8: [L3-TBL-EMBED] Tableau Embedded Analytics (count: 6) [L3-SF-AGENTIC-SEARCH] Agentic Enterprise Search (count: 4) [L3-SF-AGENTFORCE] Salesforce Agentforce (count: 2) | J8: Agentforce Builder [L3: L3-SF-AGENTFORCE, Salesforce, Low-Code] Agentforce Topics & Actions [L3: L3-SF-AGENTFORCE, Salesforce, Configuration] Agentic Enterprise Search Engine [L3: L3-SF-AGENTIC-SEARCH, Salesforce, Configuration] Federated Retrieval (Connected Sources) [L3: L3-SF-AGENTIC-SEARCH, Salesforce, API] Citations & Provenance Engine [L3: L3-SF-AGENTIC-SEARCH, Salesforce, Configuration] Search Skill in Agentforce [L3: L3-SF-AGENTIC-SEARCH, Salesforce, Configuration] Tableau Embedding API v3 [L3: L3-TBL-EMBED, Tableau, Code] Connected Apps with JWT Authentication [L3: L3-TBL-EMBED, Tableau, Configuration] VizQL Data Service (Headless Data API) [L3: L3-TBL-EMBED, Tableau, API] External Authorization Servers (EAS) [L3: L3-TBL-EMBED, Tableau, Configuration] Domain Allowlist for Embedding [L3: L3-TBL-EMBED, Tableau, Configuration] Unified Access Tokens (UATs) [L3: L3-TBL-EMBED, Tableau, Configuration] | K8: P1C1.2.2.UC2 [ALIGNMENT_LINK]: Strategy-to-execution linkage for Initiative Prioritization P1C1.2.2.UC5 [STAKEHOLDER_COMM]: Multi-channel stakeholder communication of Initiative Prioritization P1C1.2.2.UC4 [WORKFLOW_CADENCE]: Workflow-orchestrated review & refresh cycle for Initiative Prioritization P1C1.2.2.UC3 [EXEC_DASHBOARD]: Real-time executive performance dashboard for Initiative Prioritization P1C1.2.2.UC1 [AI_AUTHOR]: AI-assisted authoring & maintenance of Initiative Prioritization | L8: JIRA-IMA-118 [src: jira_completed] → UCs: P1C1.2.2.UC4 | M8: Active
A9: P1C1 | B9: Roadmap & Planning | C9: P1C1.2.3 | D9: Resource Planning | E9: Resource allocation and capacity planning for digital initiatives | F9: Hybrid | G9: T1 | H9: CIO, Program Director, Portfolio Manager, Architecture Lead | I9: [L3-TBL-EMBED] Tableau Embedded Analytics (count: 6) [L3-SF-AGENTIC-SEARCH] Agentic Enterprise Search (count: 4) [L3-SF-AGENTFORCE] Salesforce Agentforce (count: 2) | J9: Agentforce Builder [L3: L3-SF-AGENTFORCE, Salesforce, Low-Code] Agentforce Topics & Actions [L3: L3-SF-AGENTFORCE, Salesforce, Configuration] Agentic Enterprise Search Engine [L3: L3-SF-AGENTIC-SEARCH, Salesforce, Configuration] Federated Retrieval (Connected Sources) [L3: L3-SF-AGENTIC-SEARCH, Salesforce, API] Citations & Provenance Engine [L3: L3-SF-AGENTIC-SEARCH, Salesforce, Configuration] Search Skill in Agentforce [L3: L3-SF-AGENTIC-SEARCH, Salesforce, Configuration] Tableau Embedding API v3 [L3: L3-TBL-EMBED, Tableau, Code] Connected Apps with JWT Authentication [L3: L3-TBL-EMBED, Tableau, Configuration] VizQL Data Service (Headless Data API) [L3: L3-TBL-EMBED, Tableau, API] External Authorization Servers (EAS) [L3: L3-TBL-EMBED, Tableau, Configuration] Domain Allowlist for Embedding [L3: L3-TBL-EMBED, Tableau, Configuration] Unified Access Tokens (UATs) [L3: L3-TBL-EMBED, Tableau, Configuration] | K9: P1C1.2.3.UC3 [EXEC_DASHBOARD]: Real-time executive performance dashboard for Resource Planning P1C1.2.3.UC2 [ALIGNMENT_LINK]: Strategy-to-execution linkage for Resource Planning P1C1.2.3.UC1 [AI_AUTHOR]: AI-assisted authoring & maintenance of Resource Planning P1C1.2.3.UC5 [STAKEHOLDER_COMM]: Multi-channel stakeholder communication of Resource Planning P1C1.2.3.UC4 [WORKFLOW_CADENCE]: Workflow-orchestrated review & refresh cycle for Resource Planning | L9: PUB-P1C1.2.3.UC3 [src: use_case_derived_public_validated] → UCs: P1C1.2.3.UC3 PUB-P1C1.2.3.UC2 [src: use_case_derived_public_validated] → UCs: P1C1.2.3.UC2 PUB-P1C1.2.3.UC1 [src: use_case_derived_public_validated] → UCs: P1C1.2.3.UC1 PUB-P1C1.2.3.UC5 [src: use_case_derived_public_validated] → UCs: P1C1.2.3.UC5 PUB-P1C1.2.3.UC4 [src: use_case_derived_public_validated] → UCs: P1C1.2.3.UC4 | M9: Active
A10: P1C1 | B10: Roadmap & Planning | C10: P1C1.2.4 | D10: Dependency Management | E10: Identification and management of cross-initiative dependencies | F10: Hybrid | G10: T1 | H10: CIO, Program Director, Portfolio Manager, Architecture Lead | I10: [L3-TBL-EMBED] Tableau Embedded Analytics (count: 6) [L3-SF-AGENTIC-SEARCH] Agentic Enterprise Search (count: 4) [L3-SF-AGENTFORCE] Salesforce Agentforce (count: 2) | J10: Agentforce Builder [L3: L3-SF-AGENTFORCE, Salesforce, Low-Code] Agentforce Topics & Actions [L3: L3-SF-AGENTFORCE, Salesforce, Configuration] Agentic Enterprise Search Engine [L3: L3-SF-AGENTIC-SEARCH, Salesforce, Configuration] Federated Retrieval (Connected Sources) [L3: L3-SF-AGENTIC-SEARCH, Salesforce, API] Citations & Provenance Engine [L3: L3-SF-AGENTIC-SEARCH, Salesforce, Configuration] Search Skill in Agentforce [L3: L3-SF-AGENTIC-SEARCH, Salesforce, Configuration] Tableau Embedding API v3 [L3: L3-TBL-EMBED, Tableau, Code] Connected Apps with JWT Authentication [L3: L3-TBL-EMBED, Tableau, Configuration] VizQL Data Service (Headless Data API) [L3: L3-TBL-EMBED, Tableau, API] External Authorization Servers (EAS) [L3: L3-TBL-EMBED, Tableau, Configuration] Domain Allowlist for Embedding [L3: L3-TBL-EMBED, Tableau, Configuration] Unified Access Tokens (UATs) [L3: L3-TBL-EMBED, Tableau, Configuration] | K10: P1C1.2.4.UC2 [ALIGNMENT_LINK]: Strategy-to-execution linkage for Dependency Management P1C1.2.4.UC3 [EXEC_DASHBOARD]: Real-time executive performance dashboard for Dependency Management P1C1.2.4.UC1 [AI_AUTHOR]: AI-assisted authoring & maintenance of Dependency Management P1C1.2.4.UC5 [STAKEHOLDER_COMM]: Multi-channel stakeholder communication of Dependency Management P1C1.2.4.UC4 [WORKFLOW_CADENCE]: Workflow-orchestrated review & refresh cycle for Dependency Management | L10: PUB-P1C1.2.4.UC2 [src: use_case_derived_public_validated] → UCs: P1C1.2.4.UC2 PUB-P1C1.2.4.UC3 [src: use_case_derived_public_validated] → UCs: P1C1.2.4.UC3 PUB-P1C1.2.4.UC1 [src: use_case_derived_public_validated] → UCs: P1C1.2.4.UC1 PUB-P1C1.2.4.UC5 [src: use_case_derived_public_validated] → UCs: P1C1.2.4.UC5 PUB-P1C1.2.4.UC4 [src: use_case_derived_public_validated] → UCs: P1C1.2.4.UC4 | M10: Active
A11: P1C1 | B11: Roadmap & Planning | C11: P1C1.2.5 | D11: Budget Alignment | E11: Alignment of digital investment budget with strategic priorities | F11: Hybrid | G11: T1 | H11: CIO, Program Director, Portfolio Manager, Architecture Lead | I11: [L3-TBL-EMBED] Tableau Embedded Analytics (count: 6) [L3-SF-AGENTIC-SEARCH] Agentic Enterprise Search (count: 4) [L3-SF-AGENTFORCE] Salesforce Agentforce (count: 2) | J11: Agentforce Builder [L3: L3-SF-AGENTFORCE, Salesforce, Low-Code] Agentforce Topics & Actions [L3: L3-SF-AGENTFORCE, Salesforce, Configuration] Agentic Enterprise Search Engine [L3: L3-SF-AGENTIC-SEARCH, Salesforce, Configuration] Federated Retrieval (Connected Sources) [L3: L3-SF-AGENTIC-SEARCH, Salesforce, API] Citations & Provenance Engine [L3: L3-SF-AGENTIC-SEARCH, Salesforce, Configuration] Search Skill in Agentforce [L3: L3-SF-AGENTIC-SEARCH, Salesforce, Configuration] Tableau Embedding API v3 [L3: L3-TBL-EMBED, Tableau, Code] Connected Apps with JWT Authentication [L3: L3-TBL-EMBED, Tableau, Configuration] VizQL Data Service (Headless Data API) [L3: L3-TBL-EMBED, Tableau, API] External Authorization Servers (EAS) [L3: L3-TBL-EMBED, Tableau, Configuration] Domain Allowlist for Embedding [L3: L3-TBL-EMBED, Tableau, Configuration] Unified Access Tokens (UATs) [L3: L3-TBL-EMBED, Tableau, Configuration] | K11: P1C1.2.5.UC4 [WORKFLOW_CADENCE]: Workflow-orchestrated review & refresh cycle for Budget Alignment P1C1.2.5.UC3 [EXEC_DASHBOARD]: Real-time executive performance dashboard for Budget Alignment P1C1.2.5.UC2 [ALIGNMENT_LINK]: Strategy-to-execution linkage for Budget Alignment P1C1.2.5.UC1 [AI_AUTHOR]: AI-assisted authoring & maintenance of Budget Alignment P1C1.2.5.UC5 [STAKEHOLDER_COMM]: Multi-channel stakeholder communication of Budget Alignment | L11: PUB-P1C1.2.5.UC4 [src: use_case_derived_public_validated] → UCs: P1C1.2.5.UC4 PUB-P1C1.2.5.UC3 [src: use_case_derived_public_validated] → UCs: P1C1.2.5.UC3 PUB-P1C1.2.5.UC2 [src: use_case_derived_public_validated] → UCs: P1C1.2.5.UC2 PUB-P1C1.2.5.UC1 [src: use_case_derived_public_validated] → UCs: P1C1.2.5.UC1 PUB-P1C1.2.5.UC5 [src: use_case_derived_public_validated] → UCs: P1C1.2.5.UC5 | M11: Active
A12: P1C1 | B12: Segment Strategy | C12: P1C1.3.1 | D12: Customer Segment Definition | E12: Clear definition of target customer segments for digital engagement | F12: Hybrid | G12: T1 | H12: CMO, Customer Strategy Lead, LOB Heads (Banking/Wealth/Insurance), Product Manager | I12: [L3-TBL-EMBED] Tableau Embedded Analytics (count: 6) [L3-SF-DATA-CLOUD] Salesforce Data Cloud (Data 360) (count: 5) [L3-SF-AGENTIC-SEARCH] Agentic Enterprise Search (count: 5) [L3-SF-CRMA] Salesforce CRM Analytics (count: 3) [L3-SF-SLACK] Slack (count: 3) [L3-NCINO-CONSUMER] nCino Consumer Lending (count: 2) | J12: CRM Analytics Dashboards [L3: L3-SF-CRMA, Salesforce, Configuration] Einstein Discovery [L3: L3-SF-CRMA, Salesforce, Configuration] CRM Analytics Story Builder [L3: L3-SF-CRMA, Salesforce, Configuration] Zero-Copy Architecture [L3: L3-SF-DATA-CLOUD, Salesforce, Configuration] Agentic Setup and Data Management [L3: L3-SF-DATA-CLOUD, Salesforce, Configuration] Intelligent Segmentation [L3: L3-SF-DATA-CLOUD, Salesforce, Configuration] AI-Calculated Insights [L3: L3-SF-DATA-CLOUD, Salesforce, Configuration] Data 360 Activation APIs [L3: L3-SF-DATA-CLOUD, Salesforce, API] Slack Lists [L3: L3-SF-SLACK, Salesforce, Configuration] Slack Canvas [L3: L3-SF-SLACK, Salesforce, Configuration] Slack AI [L3: L3-SF-SLACK, Salesforce, OOB] Agentic Enterprise Search Engine [L3: L3-SF-AGENTIC-SEARCH, Salesforce, Configuration] Federated Retrieval (Connected Sources) [L3: L3-SF-AGENTIC-SEARCH, Salesforce, API] Permission-Aware Result Filter [L3: L3-SF-AGENTIC-SEARCH, Salesforce, Configuration] Citations & Provenance Engine [L3: L3-SF-AGENTIC-SEARCH, Salesforce, Configuration] Search Skill in Agentforce [L3: L3-SF-AGENTIC-SEARCH, Salesforce, Configuration] Auto-Decisioning Rules Engine [L3: L3-NCINO-CONSUMER, nCino, Configuration] Credit Bureau Integration [L3: L3-NCINO-CONSUMER, nCino, Configuration] Tableau Embedding API v3 [L3: L3-TBL-EMBED, Tableau, Code] Connected Apps with JWT Authentication [L3: L3-TBL-EMBED, Tableau, Configuration] VizQL Data Service (Headless Data API) [L3: L3-TBL-EMBED, Tableau, API] External Authorization Servers (EAS) [L3: L3-TBL-EMBED, Tableau, Configuration] Domain Allowlist for Embedding [L3: L3-TBL-EMBED, Tableau, Configuration] Unified Access Tokens (UATs) [L3: L3-TBL-EMBED, Tableau, Configuration] | K12: P1C1.3.1.UC4 [SELF_SERVICE_PORTAL]: Persona-based self-service portal for Customer Segment Definition P1C1.3.1.UC1 [EXEC_DASHBOARD]: Real-time executive performance dashboard for Customer Segment Definition P1C1.3.1.UC2 [DECISION_SUPPORT]: AI decision support at point of action for Customer Segment Definition P1C1.3.1.UC3 [EXTERNAL_BENCHMARK]: Peer benchmarking & calibration for Customer Segment Definition P1C1.3.1.UC5 [ALIGNMENT_LINK]: Strategy-to-execution linkage for Customer Segment Definition | L12: JIRA-AN-19 [src: jira_completed] → UCs: P1C1.3.1.UC5 JIRA-MF-448 [src: jira_completed] → UCs: P1C1.3.1.UC4, P1C1.3.1.UC1 JIRA-MOE-17 [src: jira_completed] → UCs: P1C1.3.1.UC1, P1C1.3.1.UC5 JIRA-NAVEBANK-288 [src: jira_completed] → UCs: P1C1.3.1.UC4 JIRA-PF-746 [src: jira_completed] → UCs: P1C1.3.1.UC1 JIRA-ZBFQS20-79 [src: jira_completed] → UCs: P1C1.3.1.UC1 JIRA-ZBFQS20-82 [src: jira_completed] → UCs: P1C1.3.1.UC1 | M12: Active
... A200: P1C1 | B200: Technology Strategy | C200: P1C1.5.8 | D200: Sustainable Cloud | E200: Selection and use of sustainable cloud providers | F200: Headless | G200: T1 | H200: CTO, Chief Architect, Cloud Architect, IT Strategy Lead | I200: [L3-SF-AGENTFORCE] Salesforce Agentforce (count: 2) [L3-SF-AGENTFORCE-FS] Agentforce for Financial Services (count: 1) | J200: Agentforce Builder [L3: L3-SF-AGENTFORCE, Salesforce, Low-Code] Agentforce Topics & Actions [L3: L3-SF-AGENTFORCE, Salesforce, Configuration] Embedded Compliance Controls [L3: L3-SF-AGENTFORCE-FS, Salesforce, Configuration] | K200: P1C1.5.8.UC5 [COVERAGE_MONITORING]: Coverage gap monitoring for Sustainable Cloud P1C1.5.8.UC4 [DECISION_SUPPORT]: AI decision support at point of action for Sustainable Cloud P1C1.5.8.UC3 [ALIGNMENT_LINK]: Strategy-to-execution linkage for Sustainable Cloud P1C1.5.8.UC2 [EXEC_DASHBOARD]: Real-time executive performance dashboard for Sustainable Cloud P1C1.5.8.UC1 [AI_AUTHOR]: AI-assisted authoring & maintenance of Sustainable Cloud | L200: PUB-P1C1.5.8.UC5 [src: use_case_derived_public_validated] → UCs: P1C1.5.8.UC5 PUB-P1C1.5.8.UC4 [src: use_case_derived_public_validated] → UCs: P1C1.5.8.UC4 PUB-P1C1.5.8.UC3 [src: use_case_derived_public_validated] → UCs: P1C1.5.8.UC3 PUB-P1C1.5.8.UC2 [src: use_case_derived_public_validated] → UCs: P1C1.5.8.UC2 PUB-P1C1.5.8.UC1 [src: use_case_derived_public_validated] → UCs: P1C1.5.8.UC1 | M200: Active

Sheet 3_User_Stories_Catalogue
A1: Story_Key | B1: Source_Type | C1: Source_Ref | D1: Sub_Cap_ID | E1: Sub_Cap_Name | F1: Use_Case_IDs | G1: L4_Features_Used | H1: Match_Confidence | I1: Story_Summary | J1: W_Description | K1: X_Acceptance_Criteria | L1: Y_Solution_Design | M1: Implementation_Steps | N1: Deployment_Checklist | O1: Jira_Project_URL | P1: Zennify_Effective_Status
A2: GEN-P1C2.7.1-M1M2-01 | B2: gen_stories_v1 | C2: gen_stories_export.xlsx row for GEN-P1C2.7.1-M1M2-01 | D2: P1C2.7.1 | E2: Regulatory Change Management | F2: P1C2.7.1.UC4, P1C2.7.1.UC2 | H2: HIGH | I2: As a Compliance Manager, I want to create and track regulatory changes in a central registry so that all stakeholders have visibility into upcoming and implemented regulatory requirements. | J2: Organizations need a structured way to document regulatory changes, their effective dates, and impacted business areas. This foundation enables regulatory teams to systematically track requirements and communicate them downstream. Without this, changes are communicated ad-hoc, leading to inconsistent implementation and gaps. | K2: AC1: Given a new regulatory requirement, When I create a record for the regulatory change, Then the system captures the regulation name, effective date, description, and primary impact area. AC2: Given a regulatory change record exists, When a compliance team member searches for changes by regulation type or date, Then they can view all matching records with full details. AC3: Given a regulatory change affects multiple financial products, When I link the related Financial Accounts to the change, Then the relationship is maintained for impact tracking. AC4: Given a regulatory change is created with an assigned owner, When the record is saved, Then the owner receives notification with the change summary. AC5: Given a regulatory change reaches its effective date, When the status is updated to Active, Then all assigned stakeholders receive notification that the requirement is now in effect. | L2: Overview: This story establishes the foundational regulatory change tracking system using Salesforce's core platform. It creates a central repository where compliance teams can systematically log regulatory requirements, link them to affected business areas and stakeholders, and trigger automated notifications at key lifecycle points. This enables visibility and accountability without requiring custom development. Object & Field Setup: - Create custom object [REGULATORY_CHANGE_OBJECT] to store regulatory requirement details - Add required fields: Regulation Name, Effective Date, Description, Impact Area (picklist), Status (picklist: Pending Implementation / In Progress / Active / Completed), Owner (lookup to User) - Create lookup field to link [REGULATORY_CHANGE_OBJECT] to impacted Financial Accounts - Create list view [REGULATORY_CHANGES_BY_EFFECTIVE_DATE] sorted by Effective Date to surface upcoming requirements - Create list view [REGULATORY_CHANGES_BY_STATUS] filtered by Status for progress tracking Automation: - Create Record-Triggered Flow [NOTIFY_OWNER_ON_REGULATORY_CHANGE_CREATION]: Triggers when a new record is created, sends email notification to Owner with regulation summary and deadline - Create Record-Triggered Flow [NOTIFY_STAKEHOLDERS_ON_ACTIVE_STATUS]: Triggers when Status changes to Active, sends notifications to all assigned stakeholders indicating implementation is required - Create validation rule [REGULATORY_CHANGE_REQUIRED_FIELDS]: Enforces Regulation Name, Effective Date, and Status are always populated before save Access & Permissions: - Create permission set [REGULATORY_CHANGE_MANAGER]: Grants Create, Read, Edit, Delete on [REGULATORY_CHANGE_OBJECT] - Create permission set [REGULATORY_CHANGE_VIEWER]: Grants Read-only access to [REGULATORY_CHANGE_OBJECT] - Create sharing rule to automatically share records with assigned owner - Assign [REGULATORY_CHANGE_MANAGER] to compliance/governance team; [REGULATORY_CHANGE_VIEWER] to business unit leaders | P2: {=IFERROR(XLOOKUP(D2, '2_Capability_Map'!$C$2:$C$200, '2_Capability_Map'!$M$2:$M$200, "Active"), "Active")} -> Active
A3: GEN-P1C2.7.1-M1M2-02 | B3: gen_stories_v1 | C3: gen_stories_export.xlsx row for GEN-P1C2.7.1-M1M2-02 | D3: P1C2.7.1 | E3: Regulatory Change Management | F3: P1C2.7.1.UC4, P1C2.7.1.UC2 | H3: HIGH | I3: As a Change Manager, I want to assign and track stakeholder ownership for each regulatory change so that accountability is clear and implementation progress can be monitored. | J3: Each regulatory change impacts different organizational units and roles. Assigning clear owners and linking secondary stakeholders creates accountability chains and enables the compliance team to track progress against each change. This is essential for moving from ad-hoc reactive compliance to managed change. | K3: AC1: Given a regulatory change affects multiple business units, When I assign owners to each impacted unit, Then each owner receives assignment notification with their implementation responsibility. AC2: Given a regulatory change has an assigned owner, When the owner updates the Status field, Then the system logs timestamp and owner name with the status change. AC3: Given multiple stakeholders are involved in implementing a single change, When I link secondary stakeholders to the regulatory change record, Then each stakeholder can view the change from their record relationships. AC4: Given a compliance manager needs to track ownership, When they filter the regulatory change list by owner or status, Then they see only relevant records with ownership accountability. AC5: Given a regulatory change owner is assigned, When they do not update status within 30 days of effective date, Then the system auto-generates a reminder task assigned to them. | L3: Overview: This story adds stakeholder and ownership management on top of the core regulatory change registry. It creates accountability by assigning named owners and tracking their progress, and creates relationship links to secondary stakeholders. Automation ensures timely reminders when implementation falls behind. This transforms regulatory changes from broadcast announcements into tracked, accountable work assignments. Object & Field Setup: - Add lookup field to [REGULATORY_CHANGE_OBJECT]: Primary Owner (links to User) - Add many-to-many junction object [REGULATORY_CHANGE_STAKEHOLDER] with lookup to [REGULATORY_CHANGE_OBJECT] and lookup to User to enable multiple stakeholders per change - Add field: Last Status Update Date (auto-populated by flow) - Add field: Days Since Active (formula to calculate days since Status = Active) Automation: - Create Record-Triggered Flow [ASSIGN_OWNER_AND_NOTIFY]: Triggers when Primary Owner is populated, sends email to owner with ownership acknowledgment and deadline - Create Record-Triggered Flow [LOG_STATUS_CHANGE]: Triggers on Status field update, logs the old value, new value, user, and timestamp to a status history child object - Create Record-Triggered Flow [OVERRIDE_ON_LATE_IMPLEMENTATION]: Triggers when a record has Status = Active for 30+ days, auto-generates a task [REGULATORY_CHANGE_FOLLOWUP_TASK] assigned to owner Access & Permissions: - Extend [REGULATORY_CHANGE_MANAGER] permission set to include CRUD on [REGULATORY_CHANGE_STAKEHOLDER] junction object - Create formula-based sharing to give all linked stakeholders Read access to the regulatory change record - Ensure each owner sees only the regulatory changes assigned to them via role-based sharing (or create row-level sharing rules) | P3: {=IFERROR(XLOOKUP(D3, '2_Capability_Map'!$C$2:$C$200, '2_Capability_Map'!$M$2:$M$200, "Active"), "Active")} -> Active
A4: GEN-P1C2.7.1-M1M2-03 | B4: gen_stories_v1 | C4: gen_stories_export.xlsx row for GEN-P1C2.7.1-M1M2-03 | D4: P1C2.7.1 | E4: Regulatory Change Management | F4: P1C2.7.1.UC4, P1C2.7.1.UC2 | H4: HIGH | I4: As a Compliance Communications Lead, I want to automate notifications and communications so that all relevant stakeholders are informed promptly when regulatory changes are created, updated, or approach their effective dates. | J4: Manual communication of regulatory changes is slow, inconsistent, and error-prone. Automated notifications via Salesforce alerts ensure the right people get the right information at the right time. This creates a consistent communication cadence, reduces reliance on manual emails, and ensures no stakeholder is left out of critical regulatory deadlines. | K4: AC1: Given a regulatory change is created, When the owner is assigned, Then an automated notification is sent with the regulation name, effective date, and owner assignment confirmation. AC2: Given a regulatory change has an effective date approaching, When 30 days remain before the date, Then automated alerts are sent to the primary owner and all linked stakeholders. AC3: Given a regulatory change status is updated, When the change is marked as Active, Then all stakeholders receive a notification indicating the requirement is now in effect and implementation is mandatory. AC4: Given a regulatory change has linked reference documents, When stakeholders receive a notification, Then the notification includes direct links to access those documents. AC5: Given a stakeholder is added to a regulatory change, When they are linked to the record, Then they receive a notification with full context about their role in the implementation. | L4: Overview: This story adds structured, automated communication workflows on top of the ownership model. Using Record-Triggered Flows and Alerts, it ensures stakeholders receive timely notifications at key regulatory change lifecycle points (creation, pre-effective-date, active, etc.). This eliminates gaps in communication and creates an audit trail of who was notified when. Automation: - Create Record-Triggered Flow [ALERT_30_DAYS_BEFORE_EFFECTIVE]: Triggers 30 days before Effective Date, sends email alert to Primary Owner and all stakeholders with change summary and action required - Create Record-Triggered Flow [ALERT_AT_EFFECTIVE_DATE]: Triggers on day of Effective Date, sends notification to all stakeholders that requirement is now active - Create Record-Triggered Flow [NOTIFY_ON_STAKEHOLDER_ADD]: Triggers when a stakeholder is added to [REGULATORY_CHANGE_STAKEHOLDER] junction, sends welcome notification with change context - Create Workflow Alert [REGULATORY_CHANGE_CREATION_ALERT]: Sends notification to compliance leadership when a critical regulatory change is created - Create process or flow to append notification history to the regulatory change record for audit trail Access & Permissions: - Ensure notification recipients have Read access to [REGULATORY_CHANGE_OBJECT] and linked Financial Accounts - Grant [REGULATORY_CHANGE_MANAGER] permission to create alerts and modify automation rules - Create a [NOTIFICATION_HISTORY_CHILD_OBJECT] to log all communications sent, with Create/Read permissions for auditors | P4: {=IFERROR(XLOOKUP(D4, '2_Capability_Map'!$C$2:$C$200, '2_Capability_Map'!$M$2:$M$200, "Active"), "Active")} -> Active
A5: GEN-P1C2.7.1-M1M2-04 | B5: gen_stories_v1 | C5: gen_stories_export.xlsx row for GEN-P1C2.7.1-M1M2-04 | D5: P1C2.7.1 | E5: Regulatory Change Management | F5: P1C2.7.1.UC4, P1C2.7.1.UC5 | H5: HIGH | I5: As a Process Owner, I want to identify and document which business processes and financial products are impacted by regulatory changes so that implementation teams can plan and execute their work scope. | J5: Understanding regulatory impact requires mapping requirements to affected business processes, products, and systems. Documenting this impact assessment upfront prevents rework, ensures comprehensive implementation, and gives implementation teams the information they need to plan. This transforms regulatory changes from abstract requirements into concrete implementation work. | K5: AC1: Given a regulatory change requires updates to business processes or financial products, When I create an impact assessment record linked to the regulatory change, Then it captures affected processes, product types, impacted systems, and estimated effort hours. AC2: Given an impact assessment identifies affected Financial Accounts or product types, When I link those records to the assessment, Then the system maintains relationships for downstream execution tracking. AC3: Given a regulatory change impacts multiple business processes, When I document those in the impact assessment, Then stakeholders can see the full scope of work required in their area. AC4: Given an impact assessment is completed by a process owner, When a compliance manager reviews it, Then they can approve or request refinement without modifying the original regulatory change record. AC5: Given multiple regulatory changes are in flight, When I view the impact assessments, Then I can see cross-change dependencies and potential conflicts in implementation approach. | L5: Overview: This story adds impact assessment and work-scope definition on top of the core regulatory change tracking. It creates a structured, linked object to map regulatory requirements to affected business processes, products, and systems. This enables implementation teams to understand their specific obligations without having to infer them from the regulatory requirement, and allows compliance leadership to identify conflicts or dependencies across multiple concurrent changes. Object & Field Setup: - Create custom object [REGULATORY_IMPACT_ASSESSMENT] with lookup to [REGULATORY_CHANGE_OBJECT] - Add fields: Affected Processes (multi-select), Affected Product Types (multi-select), Impacted Systems, Estimated Effort Hours, Assessment Status (picklist: Draft / In Review / Approved) - Create lookup field from [REGULATORY_IMPACT_ASSESSMENT] to Financial Account to map affected products - Add relationship to Action Plans object to enable creation of implementation work from the assessment - Create list view [REGULATORY_IMPACT_BY_PROCESS] to view all changes impacting a given business process Automation: - Create Record-Triggered Flow [COPY_IMPACT_TO_CHANGE_SUMMARY]: When impact assessment is marked Approved, updates the regulatory change record's Impact Area and linked accounts - Create Record-Triggered Flow [NOTIFY_COMPLIANCE_ON_ASSESSMENT_CREATION]: When an impact assessment is created, notifies assigned compliance reviewer Access & Permissions: - Create permission set [IMPACT_ASSESSMENT_AUTHOR]: Grants Create, Read, Edit on [REGULATORY_IMPACT_ASSESSMENT] to process owners - Create permission set [IMPACT_ASSESSMENT_REVIEWER]: Grants Read, Edit (approval field only) to compliance managers - Use field-level security to prevent process owners from modifying the regulatory change record directly | P5: {=IFERROR(XLOOKUP(D5, '2_Capability_Map'!$C$2:$C$200, '2_Capability_Map'!$M$2:$M$200, "Active"), "Active")} -> Active
A6: GEN-P1C2.7.1-M3-01 | B6: gen_stories_v1 | C6: gen_stories_export.xlsx row for GEN-P1C2.7.1-M3-01 | D6: P1C2.7.1 | E6: Regulatory Change Management | F6: P1C2.7.1.UC4, P1C2.7.1.UC1 | G6: OmniStudio, OmniScript | H6: HIGH | I6: As a Business Unit Leader, I want a self-service portal where I can view my assigned regulatory changes, understand specific impacts, and confirm my team's implementation completion so that adoption is transparent and doesn't require manual status reporting. | J6: An Experience Cloud portal for regulatory changes enables stakeholders to self-serve information and status updates, reducing administrative burden on the compliance team. It supports transparency and decentralized adoption tracking by allowing teams to confirm their implementation status without compliance staff collecting manual updates. This scales adoption management across the organization. | K6: AC1: Given a stakeholder logs into the regulatory change portal, When they view their dashboard, Then they see only regulatory changes assigned to their business unit or role. AC2: Given a regulatory change is displayed on the portal, When a stakeholder clicks to view details, Then they see the requirement, implementation deadline, their team's specific impact, and linked guidance documents. AC3: Given a stakeholder has completed implementation in their area, When they access the regulatory change, Then they can click a button to mark it as Complete for My Area and optionally add completion notes. AC4: Given a stakeholder marks a change as complete, When the action is submitted, Then the compliance team's dashboard is updated in real-time to show completion status. AC5: Given a regulatory change has linked training materials or reference documents, When a stakeholder accesses the portal, Then they can download or view these resources directly without leaving the portal. | L6: Overview: This story adds a self-service Experience Cloud portal to the M1M2 regulatory change management system. Business unit leaders can view their assigned changes, drill into impacts specific to their area, and confirm completion without waiting for manual status collection. This creates real-time visibility for the compliance team while reducing administrative overhead and empowering business units to self-manage their compliance obligations. Object & Field Setup: - Add field to [REGULATORY_CHANGE_OBJECT]: Completion Status by Area (multi-select or related list of completion records) - Create custom object [REGULATORY_CHANGE_COMPLETION] with lookup to [REGULATORY_CHANGE_OBJECT], lookup to User/Business Unit, date field, and notes field OmniStudio Configuration: - Create FlexCard [REGULATORY_CHANGE_SUMMARY_CARD] displaying regulation name, effective date, owner, and primary impact area - Create FlexCard [REGULATORY_CHANGE_ACTIONS_CARD] with action buttons: View Full Details, Mark Complete, Download Documents - Create OmniScript [REGULATORY_CHANGE_COMPLETION_FORM] to collect completion confirmation and optional notes when stakeholder marks change as complete - Create LWC or FlexCard [ASSIGNED_CHANGES_LIST] showing all regulatory changes assigned to the logged-in user's business unit Experience Cloud: - Create Experience Cloud community [REGULATORY_CHANGE_PORTAL] with custom theme and branding - Add pages: My Regulatory Changes (list of assigned), Change Details (record view with completion form), Help Center (documentation) - Configure access control to ensure business unit members see only their assigned changes (use org-wide defaults and sharing rules) Automation: - Create Record-Triggered Flow [UPDATE_COMPLETION_ON_FORM_SUBMISSION]: When [REGULATORY_CHANGE_COMPLETION] record is created, updates the parent [REGULATORY_CHANGE_OBJECT] completion tracking and notifies compliance manager | P6: {=IFERROR(XLOOKUP(D6, '2_Capability_Map'!$C$2:$C$200, '2_Capability_Map'!$M$2:$M$200, "Active"), "Active")} -> Active
A7: GEN-P1C2.7.1-M3-02 | B7: gen_stories_v1 | C7: gen_stories_export.xlsx row for GEN-P1C2.7.1-M3-02 | D7: P1C2.7.1 | E7: Regulatory Change Management | F7: P1C2.7.1.UC4, P1C2.7.1.UC2 | G7: CRM Analytics Dashboards | H7: HIGH | I7: As a Compliance Manager, I want a CRM Analytics dashboard showing regulatory change adoption rates, training completion, and implementation timelines so that I can identify bottlenecks and measure organizational readiness. | J7: Real-time visibility into adoption metrics enables proactive management of regulatory change. A CRM Analytics dashboard aggregates data from Salesforce records, action plans, and training system integrations to show which teams are on track and which need support. This enables compliance leadership to make data-driven decisions about where to focus communication and support efforts. | K7: AC1: Given regulatory change records and associated completion records exist, When the analytics dashboard loads, Then it displays overall adoption rate as a percentage of assigned stakeholders who have confirmed completion. AC2: Given a regulatory change has linked training requirements, When the dashboard is viewed, Then it shows the percentage of required staff who have completed training, with drill-down capability to department level. AC3: Given multiple regulatory changes are in flight, When a compliance manager views the dashboard, Then they see a timeline visualization showing which changes are on track to meet implementation dates and which are at risk. AC4: Given a business unit has low adoption of a regulatory change, When the manager filters the dashboard by business unit, Then they can identify which teams need targeted support and see the reasons for slower adoption. AC5: Given training completion and implementation data are updated when stakeholders take action, When a compliance officer accesses the dashboard, Then all metrics are current within 1 hour of the latest update. | L7: Overview: This story adds CRM Analytics dashboards on top of the regulatory change tracking and completion system. It aggregates adoption metrics across regulatory changes, business units, and time periods to give compliance leadership real-time visibility into organizational readiness and implementation velocity. Dashboards enable proactive intervention when adoption falls behind and data-driven measurement of change management effectiveness. CRM Analytics: - Create CRM Analytics dataset [REGULATORY_CHANGE_ANALYTICS] pulling data from [REGULATORY_CHANGE_OBJECT], [REGULATORY_CHANGE_COMPLETION], Action Plans, and training system (via integration if applicable) - Create lens [ADOPTION_RATE_BY_CHANGE]: Shows completion percentage for each regulatory change, filterable by date range and business unit - Create lens [IMPLEMENTATION_TIMELINE]: Displays Gantt-style timeline of regulatory changes by effective date, color-coded by status (on track / at risk / complete) - Create lens [TRAINING_COMPLETION_BY_DEPARTMENT]: Shows percentage of required staff completing training per regulatory change, drillable to department level - Create lens [DAYS_TO_COMPLETE_BY_CHANGE]: Calculates average days from creation to completion, identifying which change types move faster - Create dashboard [REGULATORY_CHANGE_ADOPTION_DASHBOARD] combining key lenses with filter controls for date, business unit, and regulation type Automation: - Create Record-Triggered Flow [LOG_COMPLETION_TIMESTAMP]: When [REGULATORY_CHANGE_COMPLETION] is created, captures completion timestamp for SLA reporting - Create batch process or scheduled flow to refresh dataset daily during off-hours | P7: {=IFERROR(XLOOKUP(D7, '2_Capability_Map'!$C$2:$C$200, '2_Capability_Map'!$M$2:$M$200, "Active"), "Active")} -> Active
A8: GEN-P1C2.7.1-M3-03 | B8: gen_stories_v1 | C8: gen_stories_export.xlsx row for GEN-P1C2.7.1-M3-03 | D8: P1C2.7.1 | E8: Regulatory Change Management | F8: P1C2.7.1.UC4 | H8: HIGH | I8: As a Compliance Communicator, I want to automatically generate customized regulatory change impact reports for each business unit so that stakeholders receive role-specific, actionable guidance without manual effort. | J8: Document generation tools reduce the administrative burden of creating individual impact summaries for different stakeholder groups. Automating customized report generation ensures consistency, reduces errors, and speeds communication to the field. Each business unit receives guidance tailored to their specific products, processes, and risk profile. | K8: AC1: Given a regulatory change is assigned to specific business units, When a compliance manager clicks Generate Impact Report, Then a formatted PDF document is created summarizing the requirement, timeline, business unit-specific impact, and action items. AC2: Given a report is generated, When it is created, Then it automatically includes hyperlinks to training materials, reference documents, and a contact list for questions. AC3: Given multiple regulatory changes affect the same business unit, When a manager requests a consolidated report, Then a single PDF is generated showing all active and upcoming changes prioritized by effective date. AC4: Given a regulatory change requires system updates, When an impact report is generated, Then it includes a section describing affected systems, change windows, and IT coordination requirements. AC5: Given a report is generated and stored, When a stakeholder needs it later, Then they can access the latest version from the regulatory change record without relying on email distribution. | L8: Overview: This story adds automated document generation to create customized regulatory change impact reports for different business unit audiences. Using Conga Composer or DocGen, reports are generated on-demand with business unit-specific details, linked resources, and contact information. This eliminates manual report writing, ensures consistent messaging, and gives stakeholders a tangible action guide tailored to their role and products. Integration: - Configure [DOCUMENT_GENERATION_TOOL] (Conga Composer or DocGen) connector to [REGULATORY_CHANGE_OBJECT] - Map template fields: Regulation Name, Effective Date, Description, Business Unit, Affected Processes, Affected Products, Impact Summary, Required Actions, Contact, Deadline Automation: - Create action on [REGULATORY_CHANGE_OBJECT]: Generate Impact Report button that triggers document generation - Create Record-Triggered Flow [STORE_REPORT_ON_GENERATION]: When report is generated, attach PDF to the regulatory change record and log generation event - Create optional scheduled flow to auto-generate reports for all active changes quarterly and distribute to owners Access & Permissions: - Grant [REGULATORY_CHANGE_MANAGER] permission to execute Generate Impact Report action - Configure report template access so field-level security controls what each business unit sees in their generated report | P8: {=IFERROR(XLOOKUP(D8, '2_Capability_Map'!$C$2:$C$200, '2_Capability_Map'!$M$2:$M$200, "Active"), "Active")} -> Active
A9: GEN-P1C2.7.1-M4M5-01 | B9: gen_stories_v1 | C9: gen_stories_export.xlsx row for GEN-P1C2.7.1-M4M5-01 | D9: P1C2.7.1 | E9: Regulatory Change Management | F9: P1C2.7.1.UC4, P1C2.7.1.UC2 | G9: Unified Customer Profile | H9: HIGH | I9: As a Compliance Leader, I want to use AI to analyze regulatory change text and automatically identify impacted business areas and stakeholders so that we target communications efficiently and uncover impacts we might miss through manual analysis. | J9: At M4/M5, Agentforce enables intelligent impact analysis at scale. An AI agent can parse regulatory guidance documents, cross-reference them against your unified customer and product data via Data Cloud, and recommend impacted stakeholder groups automatically. This reduces manual impact assessment time, improves consistency, and surfaces hidden impacts across complex product lines. | K9: AC1: Given a new regulatory change is created with regulatory text or a description, When an Agentforce agent is triggered, Then it analyzes the requirement against your product catalog and customer segments to identify impacted areas. AC2: Given the AI analysis identifies impacted products, business processes, or customer segments, When recommendations are generated, Then the agent suggests specific stakeholder groups and business units that should own implementation. AC3: Given impact recommendations are presented to a compliance manager, When they review AI suggestions, Then they can approve recommendations to auto-link stakeholders, or refine suggestions before saving. AC4: Given multiple regulatory changes are analyzed over a period, When the system generates comparative analysis, Then it identifies dependencies, sequencing risks, and potential conflicts in implementation approach. AC5: Given the AI has analyzed similar regulatory changes before, When a new similar change is created, Then the agent applies learnings from past implementations to accelerate impact assessment and suggest optimized communication approaches. | L9: Overview: This story adds Agentforce-driven AI impact analysis to eliminate manual regulatory change impact assessment. The agent analyzes regulatory text, cross-references Data Cloud unified customer profiles and product catalogs, and recommends impacted stakeholders automatically. This dramatically reduces assessment time, improves completeness, and enables proactive identification of indirect impacts that manual review might miss. It also learns from prior change implementations to improve recommendations over time. Agentforce Configuration: - Create Agentforce agent [REGULATORY_IMPACT_ANALYZER] with role-based access for compliance team - Configure agent instructions to: (1) Parse regulatory text provided by user, (2) Query Data Cloud [CUSTOMER_PRODUCT_DATASET] and [PRODUCT_CATALOG_DATASET] to identify matches, (3) Identify affected customer segments, products, and business processes, (4) Cross-reference against prior regulatory changes to identify patterns, (5) Recommend stakeholder groups and implementation sequence - Create tool actions for agent to: Create [REGULATORY_IMPACT_ASSESSMENT] records, Link [REGULATORY_CHANGE_STAKEHOLDER] relationships, Query CRM Analytics for historical change data - Create prompt template [REGULATORY_IMPACT_ANALYSIS_PROMPT] guiding the agent to ask clarifying questions about scope and to validate recommendations with the compliance manager Data Cloud: - Ingest [CUSTOMER_PRODUCT_DATASET]: Customer segments, products owned per segment, risk classification per product - Ingest [PRODUCT_CATALOG_DATASET]: Product names, regulatory classification, affected systems, process dependencies - Create data stream to update these datasets when new financial accounts or products are added Automation: - Create Record-Triggered Flow [TRIGGER_IMPACT_ANALYZER_ON_CREATION]: When a new [REGULATORY_CHANGE_OBJECT] record is created and Status is set to Pending Implementation, trigger the Agentforce agent with the regulation description - Create process to capture agent recommendations and store in [REGULATORY_IMPACT_ASSESSMENT] in draft status for human review | P9: {=IFERROR(XLOOKUP(D9, '2_Capability_Map'!$C$2:$C$200, '2_Capability_Map'!$M$2:$M$200, "Active"), "Active")} -> Active
A10: GEN-P1C2.7.1-M4M5-02 | B10: gen_stories_v1 | C10: gen_stories_export.xlsx row for GEN-P1C2.7.1-M4M5-02 | D10: P1C2.7.1 | E10: Regulatory Change Management | F10: P1C2.7.1.UC1, P1C2.7.1.UC2 | H10: HIGH | I10: As a Business Unit Owner, I want an AI copilot that answers my questions about regulatory change obligations and guides implementation so that I can self-serve expertise without waiting for the compliance team. | J10: Agentforce Copilot integrated with regulatory change records, training materials, and nCino Banking Advisor guidance enables business users to get instant answers to compliance questions. The agent can reference assigned changes, linked documents, training modules, and suggest next steps, dramatically reducing dependency on compliance staff and accelerating implementation velocity. | K10: AC1: Given a business unit owner views their assigned regulatory changes, When they click Ask Compliance Assistant, Then an Agentforce chat agent appears to answer questions about their specific obligations. AC2: Given a user asks What does this regulatory change require for my area, When the agent processes the question, Then it retrieves the impacted business unit from the user context and generates a role-specific answer with concrete action items. AC3: Given the agent identifies that training is required, When it formulates the response, Then it recommends the relevant training module with a direct link to access it. AC4: Given a user is implementing a regulatory change and has a follow-up question, When they ask the agent, Then it maintains conversation context and references their previous interactions and current completion status to provide relevant guidance. AC5: Given a user is asking about implementation approach, When the agent responds, Then it references similar past implementations from other business units and industry best practices to suggest optimized approaches. | L10: Overview: This story adds an Agentforce Copilot embedded in the regulatory change portal and records to provide instant, context-aware guidance to business unit owners. The agent references assigned changes, training materials, past implementations, and nCino Banking Advisor Regulatory Compliance Guidance to answer questions and guide users through implementation without requiring escalation to the compliance team. This dramatically improves time-to-implementation and reduces administrative overhead on compliance staff. Agentforce Configuration: - Create Agentforce agent [REGULATORY_CHANGE_COPILOT] deployed to Experience Cloud portal and regulatory change record pages - Configure agent persona: Regulatory Compliance Expert with deep knowledge of [CLIENT_ORG]'s products, processes, and historical implementations - Create system instruction set to: (1) Retrieve the logged-in user's business unit and assigned regulatory changes, (2) Parse questions in user context, (3) Provide role-specific guidance, (4) Recommend training and resources, (5) Suggest implementation next steps based on historical data - Create tool actions for agent to: Search [REGULATORY_CHANGE_OBJECT] and linked documents, Query training system for relevant modules, Call nCino Banking Advisor API for regulatory guidance, Query historical action plans for similar changes - Create prompt template [REGULATORY_CHANGE_GUIDANCE_PROMPT] instructing agent to always cite the specific regulation, link to supporting documents, and offer to escalate to compliance team if needed Integration: - Integrate with nCino Banking Advisor Regulatory Compliance Guidance skill: Agent can call Banking Advisor to provide regulatory interpretation and best practices - Integrate with training system (LMS): Agent can recommend and link to training modules specific to the regulatory requirement - Connect to historical implementation data: Agent queries past action plans, completion statuses, and lessons learned Experience Cloud: - Add Agentforce Copilot component to regulatory change portal pages and individual change records - Configure chat to open in a collapsible panel, allowing users to continue viewing change details while asking questions | P10: {=IFERROR(XLOOKUP(D10, '2_Capability_Map'!$C$2:$C$200, '2_Capability_Map'!$M$2:$M$200, "Active"), "Active")} -> Active
A11: GEN-P1C2.7.1-M4M5-03 | B11: gen_stories_v1 | C11: gen_stories_export.xlsx row for GEN-P1C2.7.1-M4M5-03 | D11: P1C2.7.1 | E11: Regulatory Change Management | F11: P1C2.7.1.UC4, P1C2.7.1.UC1 | G11: Einstein Discovery | H11: HIGH | I11: As a Chief Compliance Officer, I want real-time analytics showing regulatory change adoption velocity and automated triggers when adoption falls behind forecast so that we can intervene early and keep implementations on track. | J11: Data Cloud enables unified visibility into adoption metrics across Salesforce, training systems, and operational data. Advanced analytics with Einstein Discovery or embedded ML identifies adoption velocity patterns and predicts when implementations are at risk of missing deadlines, triggering automated escalations or support interventions. This transforms reactive compliance management into proactive risk mitigation. | K11: AC1: Given regulatory change implementations are underway, When the analytics engine processes completion and training data in real-time, Then it calculates adoption velocity (completion rate per business unit per day) and forecasts likely completion date. AC2: Given a regulatory change has a target implementation date, When actual adoption falls below the predicted pace required to meet the deadline, Then an automated alert is generated and escalated to the compliance manager. AC3: Given adoption velocity is at risk, When the compliance manager reviews the predictive analytics dashboard, Then the system recommends which business units need intervention and suggests targeted communications or support. AC4: Given a business unit's adoption is accelerating, When the analytics engine detects positive momentum, Then it flags this as early success and updates the confidence forecast for on-time completion in green. AC5: Given multiple regulatory changes are in progress, When the system analyzes adoption patterns across changes, Then it identifies which communication approaches, training formats, and timeline lengths drive faster adoption and recommends optimizations for future changes. | L11: Overview: This story adds advanced predictive analytics on top of the regulatory change adoption tracking system. Data Cloud aggregates completion, training, and operational data to calculate adoption velocity and forecast completion dates. Einstein Discovery or custom ML models identify adoption patterns and automatically alert the compliance team when implementations are at risk. This enables proactive intervention, reduces missed deadlines, and continuously optimizes the change management process based on empirical outcomes. Data Cloud: - Create data stream [REGULATORY_CHANGE_COMPLETION_STREAM]: Real-time updates when [REGULATORY_CHANGE_COMPLETION] records are created or updated - Create data stream [TRAINING_COMPLETION_STREAM]: Real-time training completion events from LMS integration - Ingest historical regulatory change data: Past changes, timelines, completion rates by business unit, and actual completion dates - Create calculated insights: Days to completion, adoption rate per day, business unit risk profile (prior completion patterns) CRM Analytics / Einstein Discovery: - Create recipe [ADOPTION_VELOCITY_FORECAST]: Calculates completion rate per business unit per change, compares to predicted pace, and flags at-risk changes - Create recipe [BUSINESS_UNIT_RISK_SCORING]: Scores each business unit's likelihood of on-time completion based on historical patterns and current adoption rate - Create dashboard [REGULATORY_CHANGE_INTERVENTION_DASHBOARD]: Displays at-risk changes, recommended business units for intervention, and suggested communication tactics - Configure Einstein Discovery model to identify which change characteristics (effective date, complexity, affected products) correlate with faster adoption Automation: - Create Record-Triggered Flow [FLAG_AT_RISK_CHANGE]: Monitors [REGULATORY_CHANGE_OBJECT] completion percentage and due date; when adoption falls below predicted pace, creates an Intervention Task assigned to compliance manager with recommended actions - Create scheduled flow [DAILY_ADOPTION_ANALYTICS_UPDATE]: Runs daily to recalculate forecasts and update dashboard - Create Record-Triggered Flow [ESCALATE_CRITICAL_RISK]: When adoption risk exceeds threshold (e.g., <20% completion with <7 days to deadline), sends urgent escalation to compliance officer and change sponsor Reports & Dashboards: - Create [REGULATORY_CHANGE_INTERVENTION_DASHBOARD] showing at-risk changes, recommended interventions, and adoption velocity trends - Create [ADOPTION_OPTIMIZATION_REPORT] summarizing which communication approaches, timeline lengths, and training formats drove fastest adoption in prior changes | P11: {=IFERROR(XLOOKUP(D11, '2_Capability_Map'!$C$2:$C$200, '2_Capability_Map'!$M$2:$M$200, "Active"), "Active")} -> Active
A12: GEN-P1C2.7.2-M1M2-01 | B12: gen_stories_v1 | C12: gen_stories_export.xlsx row for GEN-P1C2.7.2-M1M2-01 | D12: P1C2.7.2 | E12: Compliance Governance | F12: P1C2.7.2.UC4, P1C2.7.2.UC2 | H12: HIGH | I12: As a Chief Compliance Officer, I want to establish a compliance governance structure with defined roles, responsibilities, and decision authorities so that compliance decisions are made by the right people with clear accountability. | J12: This story establishes the foundational Salesforce framework for compliance governance. It creates objects to represent the compliance committee structure, committee members, and decision authority levels. Organizations need a clear organizational structure with defined roles (e.g., Committee Chair, Committee Member, Compliance Officer) and a RACI matrix to ensure that key compliance decisions are made by appropriate authorities. This prevents decision-making bottlenecks and ensures accountability. | K12: AC1: Given a compliance committee is created in Salesforce, When a user with [PROFILE_CCO] role logs in, Then they can view and edit the committee structure including members, roles, and term dates on [PAGE_LAYOUT_GOVERNANCE]. AC2: Given compliance roles are defined (Chair, Vice-Chair, Member, Compliance Officer), When users are assigned to a [PERMISSION_SET_COMPLIANCE_ROLE], Then they can only view governance records and access decision tracking for their assigned committees. AC3: Given a RACI matrix is configured for compliance decisions, When a compliance decision record is created with a Decision_Type__c, Then the system auto-populates the Responsible, Accountable, Consulted, and Informed roles from the RACI matrix. AC4: Given committee membership changes occur, When a member's End_Date__c is reached, Then the system automatically marks the member record as inactive and removes them from future meeting notifications. AC5: Given someone without proper authorization attempts to approve a compliance decision, When they click the approval button, Then the system prevents the action with a message showing their insufficient authority level. AC6: Given committee members are assigned to a compliance committee, When the meeting is scheduled, Then all assigned members automatically receive a notification with meeting details, agenda, and their assigned pre-meeting tasks. | L12: Overview: This story creates the core governance objects and permission structure in Salesforce to establish clear compliance governance. The solution implements custom objects for governance committees, members, and decision authority levels, combined with permission sets that enforce role-based access. This provides the structural foundation for all downstream compliance governance activities and ensures decisions are tracked and assigned to the appropriate authority. Object & Field Setup: - Create custom object [GOVERNANCE_COMMITTEE_OBJECT]: Compliance_Governance_Committee__c with fields: - Committee_Name__c (text, required) - Committee_Type__c (picklist: Executive, Risk, Audit, Regulatory, Other) - Chair_User__c (lookup to User) - Charter_Document__c (file) - Meeting_Frequency__c (picklist: Weekly, Monthly, Quarterly, As-Needed) - Is_Active__c (checkbox) - Create custom object [COMMITTEE_MEMBER_OBJECT]: Compliance_Committee_Member__c with fields: - Committee__c (master-detail to Compliance_Governance_Committee__c) - Member_User__c (lookup to User) - Role__c (picklist: Chair, Vice-Chair, Member, Secretary) - Start_Date__c (date) - End_Date__c (date) - Is_Active__c (checkbox) - Create custom object [DECISION_RACI_OBJECT]: Compliance_Decision_RACI__c with fields: - Decision_Type__c (picklist: Policy Approval, Risk Escalation, Control Exception, Regulatory Update, Remediation, Other) - Responsible_Role__c (text) - Accountable_Role__c (text, required) - Consulted_Roles__c (long text area) - Informed_Roles__c (long text area) Automation: - Create record-triggered flow [FLOW_POPULATE_RACI] that fires when a compliance decision record is created; looks up the Decision_Type__c in the RACI matrix and auto-populates Responsible, Accountable, Consulted, and Informed fields - Create scheduled flow [FLOW_DEACTIVATE_EXPIRED_MEMBERS] that runs daily; sets Is_Active__c to false for any Compliance_Committee_Member__c where End_Date__c is less than today - Create record-triggered flow [FLOW_NOTIFY_COMMITTEE] that fires when a [MEETING_OBJECT] is created; sends notifications to all active committee members with meeting details Access & Permissions: - Create permission set [PERMISSION_SET_CCO] granting full CRUD on Compliance_Governance_Committee__c, read/write on Compliance_Committee_Member__c, and read on Compliance_Decision_RACI__c - Create permission set [PERMISSION_SET_COMPLIANCE_OFFICER] granting read/write on governance and decision records, read on committee records - Create permission set [PERMISSION_SET_COMMITTEE_MEMBER] granting read-only access to assigned committee and decision records - Use role hierarchy to ensure read access is limited to records for the user's assigned committee(s) - Create sharing rule [SHARING_RULE_COMMITTEE_MEMBERS] to share committee records with all active members | P12: {=IFERROR(XLOOKUP(D12, '2_Capability_Map'!$C$2:$C$200, '2_Capability_Map'!$M$2:$M$200, "Active"), "Active")} -> Active
A13: GEN-P1C2.7.2-M1M2-02 | B13: gen_stories_v1 | C13: gen_stories_export.xlsx row for GEN-P1C2.7.2-M1M2-02 | D13: P1C2.7.2 | E13: Compliance Governance | F13: P1C2.7.2.UC4, P1C2.7.2.UC2 | H13: HIGH | I13: As a Compliance Officer, I want to centrally manage compliance policies and procedures with version control and approval workflows so that the organization has a single source of truth and knows which policies are current and approved. | J13: Organizations need a centralized repository for compliance policies and procedures that enables version control, tracks approval history, and restricts access based on role. This story creates a document management structure within Salesforce that allows policies to be authored, reviewed, approved by appropriate committees, and published. It ensures that outdated policies are clearly marked as superseded and that access is controlled appropriately. | K13: AC1: Given a compliance policy is created in Salesforce, When a Compliance Officer uploads a policy document and sets the Status__c to 'Draft', Then the system creates a version 1.0 record and enables only the author and [PERMISSION_SET_CCO] users to view and edit it. AC2: Given a policy is ready for review, When the Compliance Officer changes the Status__c to 'Ready for Review', Then the system routes the policy to the appropriate [COMMITTEE_NAME] for approval through a workflow task and notifies committee members. AC3: Given a committee approves a policy, When the approver clicks 'Approve' on the policy record, Then the system increments the version number, records the approval date and approver, sets Status__c to 'Approved', and publishes the policy for access by [POLICY_AUDIENCE]. AC4: Given a policy is superseded by a new version, When a new policy with the same Policy_ID__c is approved, Then the system automatically marks the previous version's Status__c as 'Superseded' and creates a link between versions. AC5: Given a user searches for a compliance policy, When they access the [POLICY_PORTAL_OR_LIST], Then they only see currently approved policies and are unable to see draft or superseded versions unless they have [PERMISSION_SET_CCO]. AC6: Given a policy needs to be updated, When the policy is already in 'Approved' status and an author initiates a revision, Then the system creates a new version record with status 'Draft' and keeps the prior approved version accessible during the review period. AC7: Given a policy requires periodic review, When the Effective_From__c plus Review_Frequency__c equals today, Then the system creates a task assigned to the [POLICY_OWNER_ROLE] to review and recertify the policy. | L13: Overview: This story implements a policy and procedure repository in Salesforce with built-in version control and approval workflows. The solution creates a custom object for policies with status tracking, approval routing, and versioning logic. It ensures that only currently approved policies are accessible to the organization, maintains a complete audit trail of approvals and changes, and enforces role-based access control throughout the policy lifecycle. Object & Field Setup: - Create custom object [POLICY_OBJECT]: Compliance_Policy__c with fields: - Policy_Name__c (text, required) - Policy_ID__c (text, external ID, required) - Policy_Type__c (picklist: Regulatory, Operational, Risk Management, Other) - Description__c (long text area) - Effective_From__c (date, required) - Effective_To__c (date) - Current_Version__c (number, formula: MAX(Version__c)) - Review_Frequency__c (picklist: Monthly, Quarterly, Annually, Every 2 Years) - Policy_Owner__c (lookup to User) - Assigned_Committee__c (lookup to Compliance_Governance_Committee__c) - Status__c (picklist: Draft, Ready for Review, Approved, Superseded) - Approval_Date__c (date) - Approved_By__c (lookup to User) - Create custom object [POLICY_VERSION_OBJECT]: Compliance_Policy_Version__c with fields: - Policy__c (master-detail to Compliance_Policy__c, cascade delete disabled) - Version_Number__c (number) - Version_Date__c (date) - Document_URL__c (URL or file field) - Status__c (picklist: Draft, Under Review, Approved, Superseded) - Prior_Version__c (lookup to Compliance_Policy_Version__c) - Approval_Comments__c (long text area) Automation: - Create record-triggered flow [FLOW_CREATE_POLICY_VERSION] that fires when Compliance_Policy__c Status__c changes to 'Approved'; creates a new Compliance_Policy_Version__c record with incremented Version_Number__c and sets Approval_Date__c and Approved_By__c - Create record-triggered flow [FLOW_ROUTE_POLICY_FOR_APPROVAL] that fires when Status__c changes to 'Ready for Review'; creates a workflow task assigned to the Assigned_Committee__c Chair and notifies committee members - Create record-triggered flow [FLOW_MARK_SUPERSEDED] that fires when a new policy version is approved; finds the prior version and sets its Status__c to 'Superseded' and creates a link via Prior_Version__c - Create scheduled flow [FLOW_POLICY_REVIEW_DUE] that runs daily; identifies policies where Effective_From__c + Review_Frequency__c equals today and creates a task for the Policy_Owner__c Access & Permissions: - Create permission set [PERMISSION_SET_POLICY_AUTHOR] allowing CRUD on Policy__c and Policy_Version__c in draft status only - Create permission set [PERMISSION_SET_COMPLIANCE_OFFICER] allowing read/write on Policy__c and approval of policies via workflow - Create permission set [PERMISSION_SET_POLICY_VIEWER] allowing read-only access to approved policies only - Use validation rule [VALIDATION_POLICY_STATUS] to prevent Draft policies from being viewed by users without authorship or [PERMISSION_SET_CCO] - Create sharing rule [SHARING_RULE_POLICY_DRAFT] to share draft policies only with Policy_Owner__c and assigned committee members | P13: {=IFERROR(XLOOKUP(D13, '2_Capability_Map'!$C$2:$C$200, '2_Capability_Map'!$M$2:$M$200, "Active"), "Active")} -> Active
A14: GEN-P1C2.7.2-M1M2-03 | B14: gen_stories_v1 | C14: gen_stories_export.xlsx row for GEN-P1C2.7.2-M1M2-03 | D14: P1C2.7.2 | E14: Compliance Governance | F14: P1C2.7.2.UC4, P1C2.7.2.UC5 | H14: HIGH | I14: As a Risk Officer, I want to create and maintain a compliance risk register so that all identified compliance risks are tracked, owned, and monitored for status and remediation progress. | J14: Compliance governance requires a centralized risk register where compliance risks are identified, assigned ownership, prioritized, and tracked to closure. This story creates the foundational risk object and basic tracking capabilities to enable proactive risk management. Risks should be tied to regulatory requirements or control objectives, assigned to responsible parties, and tracked with status and remediation action items. | K14: AC1: Given a compliance risk is identified, When a user creates a [RISK_OBJECT] record, Then the system requires Risk_Description__c, Owner__c, and Initial_Risk_Rating__c (High/Medium/Low) and auto-populates Created_Date__c. AC2: Given a risk is created, When the risk record is saved, Then the system routes a notification to the assigned Owner__c and the [COMMITTEE_NAME] Chair informing them of the new risk. AC3: Given a risk is tracked in the register, When a user views the [RISK_REGISTER_REPORT], Then they see all active risks grouped by status (Identified, In Progress, Mitigated, Closed) and sorted by Risk_Rating__c (High first). AC4: Given a risk owner is working on remediation, When they update Status__c to 'In Progress' and link remediation Action_Items__c, Then the system creates a task for each action item assigned to the responsible party with the Due_Date__c. AC5: Given a risk has remediation actions, When all associated action items are closed and the owner updates Status__c to 'Mitigated', Then the system captures the Mitigation_Date__c and sends a notification to the assigned committee for review. AC6: Given a risk is being reviewed, When the assigned committee approves the risk closure, When they click 'Approve Closure' on the risk record, Then the system sets Status__c to 'Closed', captures Closed_Date__c and Closed_By__c, and archives the risk record from active view. AC7: Given a risk register is maintained over time, When a manager views the [RISK_METRICS_REPORT], Then they see metrics such as 'Number of Open Risks', 'Average Time to Mitigation', 'Risks by Category', and 'Trends (open/closed over time)'. | L14: Overview: This story establishes the compliance risk register using a core Salesforce custom object, enabling the organization to identify, own, track, and remediate compliance risks. The solution creates a risk object linked to owners and remediation actions, implements status tracking workflows, and provides basic reporting. This ensures risks are visible, owned, and monitored until closure, forming the foundation for proactive compliance risk management. Object & Field Setup: - Create custom object [RISK_OBJECT]: Compliance_Risk__c with fields: - Risk_Name__c (text, required) - Risk_Description__c (long text area, required) - Risk_Category__c (picklist: Regulatory, Operational, Reputational, Control, Other) - Identified_Date__c (date, required) - Owner__c (lookup to User, required) - Escalation_Owner__c (lookup to User) - Initial_Risk_Rating__c (picklist: Critical, High, Medium, Low) - Current_Risk_Rating__c (picklist: Critical, High, Medium, Low) - Status__c (picklist: Identified, In Progress, Mitigated, Closed) - Regulatory_Reference__c (text) - Root_Cause__c (long text area) - Mitigation_Strategy__c (long text area) - Mitigation_Date__c (date) - Closed_Date__c (date) - Closed_By__c (lookup to User) - Related_Policies__c (text, multi-select picklist) - Related_Controls__c (lookup to [CONTROL_OBJECT]) - Create custom object [RISK_ACTION_ITEM_OBJECT]: Compliance_Risk_Action__c with fields: - Risk__c (master-detail to Compliance_Risk__c) - Action_Title__c (text, required) - Description__c (text area) - Assigned_To__c (lookup to User, required) - Due_Date__c (date, required) - Status__c (picklist: Not Started, In Progress, Complete, Overdue) - Completion_Date__c (date) Automation: - Create record-triggered flow [FLOW_NOTIFY_RISK_OWNER] that fires when Compliance_Risk__c is created; sends email to Owner__c and committee members notifying them of the new risk - Create record-triggered flow [FLOW_CREATE_RISK_ACTIONS] that fires when Compliance_Risk_Action__c is created; creates a task in Salesforce for the Assigned_To__c user with the Due_Date__c - Create record-triggered flow [FLOW_UPDATE_RISK_STATUS] that fires when Compliance_Risk__c Status__c changes to 'In Progress'; checks that at least one Compliance_Risk_Action__c is linked; if none, shows an error - Create scheduled flow [FLOW_CHECK_OVERDUE_ACTIONS] that runs daily; identifies Compliance_Risk_Action__c records where Status__c is not 'Complete' and Due_Date__c is past today, then updates Status__c to 'Overdue' - Create record-triggered flow [FLOW_NOTIFY_CLOSURE_REVIEW] that fires when Compliance_Risk__c Status__c changes to 'Mitigated'; notifies the assigned committee that the risk is ready for closure review Access & Permissions: - Create permission set [PERMISSION_SET_RISK_OFFICER] granting full CRUD on Compliance_Risk__c and Compliance_Risk_Action__c - Create permission set [PERMISSION_SET_RISK_OWNER] granting read/write on risks owned by the user and read-only on all other risks - Create permission set [PERMISSION_SET_COMMITTEE_RISK_REVIEW] granting read access to all risks and ability to approve risk closures - Use role hierarchy to ensure users can view risks relevant to their department/function Reports & Dashboards: - Create report [RISK_REGISTER_REPORT]: Compliance Risk register filtered by Status__c, grouped by Status, sorted by Current_Risk_Rating__c descending - Create report [OVERDUE_ACTIONS_REPORT]: Compliance Risk Action Items filtered by Status__c 'Overdue', showing Risk Name, Due Date, Assigned To - Create dashboard [RISK_METRICS_DASHBOARD] with components: - Gauge: Count of Critical/High risks - Bar chart: Risks by category - Trend chart: Open vs. closed risks over 12 months - Table: Top 10 overdue actions | P14: {=IFERROR(XLOOKUP(D14, '2_Capability_Map'!$C$2:$C$200, '2_Capability_Map'!$M$2:$M$200, "Active"), "Active")} -> Active
A15: GEN-P1C2.7.2-M1M2-04 | B15: gen_stories_v1 | C15: gen_stories_export.xlsx row for GEN-P1C2.7.2-M1M2-04 | D15: P1C2.7.2 | E15: Compliance Governance | F15: P1C2.7.2.UC4, P1C2.7.2.UC2 | H15: HIGH | I15: As a Compliance Officer, I want to implement approval workflows for compliance decisions so that decisions are routed to the appropriate authority based on decision type and are tracked with full audit history. | J15: Compliance governance requires that key decisions (e.g., policy approvals, control exceptions, risk escalations) be routed to and approved by the appropriate authority based on their type and scope. This story creates a decision tracking object and approval workflows that enforce the RACI matrix established in earlier stories. Approvals must be tracked with timestamps, approver identity, and comments for audit purposes. | K15: AC1: Given a compliance decision is initiated, When a user creates a [DECISION_OBJECT] with Decision_Type__c (e.g., 'Policy Approval'), Then the system looks up the RACI matrix, auto-populates the Accountable_Role__c, and routes the decision to the appropriate [APPROVER_QUEUE] or user. AC2: Given a decision is routed for approval, When the decision record is created, Then the system sends a notification to the Accountable_Role__c user showing the decision details, Decision_Type__c, business rationale, and a link to approve/reject. AC3: Given an approver receives a decision for review, When they click 'Approve' or 'Reject', Then the system records the approval date/time, approver identity, and any approval comments in an [APPROVAL_HISTORY_OBJECT] record. AC4: Given a decision requires multiple approval levels (e.g., Committee Review then Executive Sign-off), When the first approver approves, Then the system automatically routes the decision to the next approver based on the Decision_Approval_Chain__c configuration. AC5: Given a decision is pending approval and the due date is approaching, When 3 days remain until Due_Date__c, Then the system sends a reminder email to the assigned approver. AC6: Given a decision has been rejected by an approver, When the rejection is submitted, Then the system sets Status__c to 'Rejected', notifies the originator of the rejection and feedback, and routes the decision back to the originating [QUEUE_NAME] for revision. AC7: Given a decision is approved, When all required approvals are obtained, Then the system sets Status__c to 'Approved' and executes any post-approval automation (e.g., publishing a policy, escalating a risk). | L15: Overview: This story implements a compliance decision approval workflow using Salesforce custom objects and flows. The solution creates a decision object linked to the RACI matrix, implements approval routing based on decision type, and captures full audit history of all approvals. Decisions are tracked through their lifecycle (Initiated → Under Review → Approved/Rejected), with automatic routing to the next approver and notifications at each stage. This ensures that all compliance decisions are made by the appropriate authority and fully audited. Object & Field Setup: - Create custom object [DECISION_OBJECT]: Compliance_Decision__c with fields: - Decision_Name__c (text, required) - Decision_Type__c (picklist: Policy Approval, Control Exception, Risk Escalation, Regulatory Change, Remediation Approval, Other) - Description__c (long text area, required) - Business_Rationale__c (long text area) - Initiated_Date__c (date, auto-filled = TODAY()) - Initiated_By__c (lookup to User, auto-filled = $User.Id) - Due_Date__c (date) - Status__c (picklist: Initiated, Under Review, Approved, Rejected, Withdrawn) - Related_Policy__c (lookup to [POLICY_OBJECT]) - Related_Risk__c (lookup to Compliance_Risk__c) - Related_Exception__c (lookup to [EXCEPTION_OBJECT]) - Approval_Chain_Config__c (lookup to [APPROVAL_CHAIN_CONFIG_OBJECT]) - Current_Approver_Role__c (text, formula from RACI lookup) - Current_Approver_User__c (lookup to User) - Create custom object [APPROVAL_HISTORY_OBJECT]: Compliance_Approval_History__c with fields: - Decision__c (master-detail to Compliance_Decision__c) - Approval_Sequence__c (number) - Approver_Role__c (text) - Approver_User__c (lookup to User) - Action__c (picklist: Approved, Rejected, Escalated, Withdrawn) - Approval_Date__c (date/time) - Comments__c (long text area) - Attachment__c (file field) - Create custom object [APPROVAL_CHAIN_CONFIG_OBJECT]: Compliance_Approval_Chain_Config__c with fields: - Decision_Type__c (picklist) - Approval_Level__c (number) - Approver_Role__c (text) - Can_Delegate__c (checkbox) - Escalation_User__c (lookup to User) Automation: - Create record-triggered flow [FLOW_ROUTE_DECISION] that fires when Compliance_Decision__c Status__c changes to 'Under Review'; looks up the next approver from [APPROVAL_CHAIN_CONFIG_OBJECT] based on Decision_Type__c, sets Current_Approver_User__c, and creates a workflow task - Create record-triggered flow [FLOW_NOTIFY_APPROVER] that fires when Compliance_Decision__c is created or approval is routed; sends email to Current_Approver_User__c with decision details and link to approve/reject - Create record-triggered flow [FLOW_RECORD_APPROVAL] that fires when approval action is submitted; creates Compliance_Approval_History__c record with Action__c, Approver_User__c, and Approval_Date__c - Create record-triggered flow [FLOW_ROUTE_NEXT_APPROVAL] that fires when Compliance_Approval_History__c is created with Action__c = 'Approved'; checks if there is a next approval level; if yes, routes to next approver; if no, sets Compliance_Decision__c Status__c to 'Approved' - Create record-triggered flow [FLOW_HANDLE_REJECTION] that fires when Compliance_Approval_History__c Action__c = 'Rejected'; sets Compliance_Decision__c Status__c to 'Rejected' and notifies Initiated_By__c with feedback - Create scheduled flow [FLOW_SEND_APPROVAL_REMINDERS] that runs daily at 9:00 AM; identifies decisions where Status__c = 'Under Review' and Due_Date__c is ≤ 3 days away; sends reminder email to Current_Approver_User__c Access & Permissions: - Create permission set [PERMISSION_SET_DECISION_INITIATOR] allowing create/read on Compliance_Decision__c - Create permission set [PERMISSION_SET_APPROVER] allowing read/write on decisions assigned to the user for approval - Create permission set [PERMISSION_SET_COMPLIANCE_ADMIN] allowing full CRUD on Compliance_Decision__c and Compliance_Approval_History__c - Use Record-Triggered Flow [WORKFLOW_LOCK_DECISION] to prevent editing of Compliance_Decision__c fields once Status__c changes from 'Initiated' (except by approvers) Reports & Dashboards: - Create report [DECISION_APPROVAL_STATUS_REPORT]: Compliance_Decision__c filtered by Status__c, showing Decision_Name, Type, Current_Approver_Role, Days Pending - Create report [APPROVAL_AUDIT_TRAIL_REPORT]: Compliance_Approval_History__c showing Decision_Name, Approver, Action, Date, Comments | P15: {=IFERROR(XLOOKUP(D15, '2_Capability_Map'!$C$2:$C$200, '2_Capability_Map'!$M$2:$M$200, "Active"), "Active")} -> Active
A16: GEN-P1C2.7.2-M1M2-05 | B16: gen_stories_v1 | C16: gen_stories_export.xlsx row for GEN-P1C2.7.2-M1M2-05 | D16: P1C2.7.2 | E16: Compliance Governance | F16: P1C2.7.2.UC5, P1C2.7.2.UC4 | H16: HIGH | I16: As a Compliance Officer, I want to track compliance action items and tasks from committee meetings and reviews so that commitments are assigned, monitored, and closed with clear accountability. | J16: Compliance governance requires that action items assigned during committee meetings and compliance reviews are tracked and monitored to completion. This story creates a task management structure for compliance action items, linked to their source (e.g., committee meeting, audit finding), assigned to owners with due dates, and tracked through to closure with status visibility. | K16: AC1: Given a compliance committee meeting is held, When action items are identified and documented in the meeting minutes, Then a user can create [COMPLIANCE_ACTION_ITEM_OBJECT] records linked to the meeting and assign each to an owner with a due date. AC2: Given a compliance action item is created, When the action item record is saved, Then the system auto-populates Created_Date__c, sends a notification to the assigned owner with details, and creates a Salesforce task for tracking. AC3: Given an action item owner is working on the item, When they update Status__c to 'In Progress', Then the system records the Start_Date__c and notifies any stakeholders flagged in the Notify_On_Progress__c field. AC4: Given an action item is completed, When the owner updates Status__c to 'Complete' and adds a Completion_Comment__c, Then the system auto-fills Completion_Date__c, notifies the originating committee, and archives the action item from the active list. AC5: Given an action item is overdue, When the current date exceeds the Due_Date__c and Status__c is not 'Complete', Then the system updates Status__c to 'Overdue' and sends a daily reminder to the owner until completion. AC6: Given a manager views the [ACTION_ITEM_DASHBOARD], Then they see metrics including 'Total Open Items', 'Overdue Count', 'Items by Status', and 'Average Days to Complete'. AC7: Given an action item is linked to a compliance risk or policy, When viewing the risk or policy record, Then the related action items are displayed and the status is visible in context. | L16: Overview: This story implements compliance action item tracking using a custom Salesforce object with status workflows, notifications, and status dashboards. The solution enables action items to be created from committee meetings or compliance reviews, assigned to owners with due dates, tracked through to completion, and reported on. This ensures that compliance commitments are formalized, owned, monitored, and completed with full visibility. Object & Field Setup: - Create custom object [COMPLIANCE_ACTION_ITEM_OBJECT]: Compliance_Action_Item__c with fields: - Action_Title__c (text, required) - Description__c (long text area) - Source__c (picklist: Committee Meeting, Audit Finding, Policy Review, Regulatory Change, Control Testing) - Related_Meeting__c (lookup to [MEETING_OBJECT]) - Related_Risk__c (lookup to Compliance_Risk__c) - Related_Audit_Finding__c (lookup to [AUDIT_FINDING_OBJECT]) - Status__c (picklist: Assigned, In Progress, Complete, Overdue, On Hold) - Owner__c (lookup to User, required) - Created_Date__c (date, auto-filled) - Created_By__c (lookup to User, auto-filled) - Due_Date__c (date, required) - Start_Date__c (date) - Completion_Date__c (date) - Completion_Comment__c (long text area) - Priority__c (picklist: Critical, High, Medium, Low) - Notify_On_Progress__c (email lookup field or text field) - Days_Overdue__c (number, formula: IF(Status__c = 'Overdue', TODAY() - Due_Date__c, 0)) Automation: - Create record-triggered flow [FLOW_CREATE_ACTION_TASK] that fires when Compliance_Action_Item__c is created; creates a Salesforce task assigned to Owner__c with Due_Date__c and description from Action_Title__c - Create record-triggered flow [FLOW_NOTIFY_ACTION_OWNER] that fires when Compliance_Action_Item__c is created; sends email to Owner__c with action details and link to update - Create record-triggered flow [FLOW_NOTIFY_ON_PROGRESS] that fires when Status__c changes to 'In Progress'; sends email to users listed in Notify_On_Progress__c field - Create record-triggered flow [FLOW_MARK_OVERDUE] that fires when Status__c is not 'Complete' and today exceeds Due_Date__c; updates Status__c to 'Overdue' and sends email to Owner__c - Create record-triggered flow [FLOW_NOTIFY_ON_COMPLETION] that fires when Status__c changes to 'Complete'; sends confirmation email to Related_Meeting__c Committee Chair and creates a completion record - Create scheduled flow [FLOW_SEND_OVERDUE_REMINDERS] that runs daily at 9:00 AM; identifies overdue items (Status__c = 'Overdue' and Days_Overdue__c > 0) and sends daily reminder email to Owner__c Access & Permissions: - Create permission set [PERMISSION_SET_ACTION_CREATOR] allowing create/read on Compliance_Action_Item__c - Create permission set [PERMISSION_SET_ACTION_OWNER] allowing read/write on action items owned by or assigned to the user - Create permission set [PERMISSION_SET_ACTION_MONITOR] allowing read-only access to all action items - Create sharing rule [SHARING_RULE_ACTION_ITEMS] to share action items with the owner and committee members Reports & Dashboards: - Create report [ACTION_ITEM_STATUS_REPORT]: Compliance_Action_Item__c showing Owner, Status, Due Date, sorted by Priority and Due Date - Create report [OVERDUE_ACTIONS_REPORT]: Compliance_Action_Item__c filtered to Status__c = 'Overdue', showing Owner, Days Overdue, Action Title - Create dashboard [ACTION_ITEM_DASHBOARD] with components: - Gauge: Total open action items - Gauge: Overdue count - Pie chart: Items by Status - Bar chart: Items by Owner - Trend: Average days to completion (over rolling 12 months) | P16: {=IFERROR(XLOOKUP(D16, '2_Capability_Map'!$C$2:$C$200, '2_Capability_Map'!$M$2:$M$200, "Active"), "Active")} -> Active
A17: GEN-P1C2.7.2-M1M2-06 | B17: gen_stories_v1 | C17: gen_stories_export.xlsx row for GEN-P1C2.7.2-M1M2-06 | D17: P1C2.7.2 | E17: Compliance Governance | F17: P1C2.7.2.UC4, P1C2.7.2.UC2 | H17: HIGH | I17: As a Compliance Administrator, I want to implement an audit trail and change log for compliance governance records so that all changes to compliance decisions, policies, and risks are tracked with full visibility into who made what changes and when. | J17: Regulatory requirements demand that compliance governance activities be auditable and that all changes are logged with timestamps and user identity. This story implements an audit trail mechanism using Salesforce's change tracking features and custom audit objects. All modifications to key compliance records (policies, decisions, risks, action items) are logged automatically, enabling compliance teams to demonstrate audit readiness and investigate compliance issues. | K17: AC1: Given compliance governance records are created and updated, When a user makes a change to a compliance record, Then the system automatically logs the change with record ID, field name, old value, new value, user ID, and timestamp in [AUDIT_LOG_OBJECT]. AC2: Given a policy is approved, When the approver clicks 'Approve', Then the system creates an audit log entry showing Policy ID, 'Status Changed to Approved', approver ID, timestamp, and approval rationale from Approval_Comments__c. AC3: Given a decision is routed for approval, When approval routing occurs, Then the system logs the routing event with Decision ID, new Approver Role, timestamp, and any escalation details. AC4: Given a risk is created or updated, When any field in Compliance_Risk__c is changed, Then the system logs the change including Risk ID, changed field, prior value, new value, user, and timestamp. AC5: Given a user needs to review change history, When they view the [AUDIT_TRAIL_REPORT] for a compliance record, Then they see a chronological list of all changes with user, timestamp, and field changes, formatted for compliance review. AC6: Given compliance data is accessed, When a user views or exports compliance records, Then the system logs access events (view, export, report run) with user ID, timestamp, and record IDs accessed. AC7: Given an audit is requested, When an auditor runs the [COMPLIANCE_AUDIT_REPORT], Then they can filter audit logs by date range, user, record type, and action type (Create, Update, Approve, Delete). | L17: Overview: This story implements a comprehensive audit trail using Salesforce change tracking and a custom audit log object. The solution captures all changes to key compliance records (policies, decisions, risks, action items) automatically through field history tracking and custom flows. All audit data is logged to a centralized audit object, enabling forensic analysis, compliance verification, and audit readiness. This ensures the organization can demonstrate the who, what, when, and why of all compliance governance activities. Object & Field Setup: - Create custom object [AUDIT_LOG_OBJECT]: Compliance_Audit_Log__c with fields: - Record_Type__c (picklist: Policy, Decision, Risk, Action Item, Committee, Approval) - Record_ID__c (text) - Record_Name__c (text) - Action__c (picklist: Created, Updated, Deleted, Approved, Rejected, Approved, Escalated) - Field_Name__c (text) - Old_Value__c (long text area) - New_Value__c (long text area) - User_ID__c (lookup to User) - User_Name__c (text, formula) - Change_DateTime__c (date/time, auto-filled = NOW()) - Change_Reason__c (long text area) - Access_Type__c (picklist: View, Export, Report, Download) - IP_Address__c (text) - Enable field history tracking on key Compliance_Policy__c fields (Status, Approval_Date, Approved_By, Effective_To) - Enable field history tracking on key Compliance_Decision__c fields (Status, Current_Approver_User, approval-related fields) - Enable field history tracking on key Compliance_Risk__c fields (Status, Owner, Current_Risk_Rating, Mitigation_Date, Closed_Date) - Enable field history tracking on key Compliance_Action_Item__c fields (Status, Owner, Completion_Date) Automation: - Create record-triggered flow [FLOW_LOG_POLICY_CHANGES] that fires on all changes to Compliance_Policy__c; creates Compliance_Audit_Log__c entry with Record_Type = 'Policy', Action based on Status change, and field-level change details - Create record-triggered flow [FLOW_LOG_DECISION_CHANGES] that fires on all changes to Compliance_Decision__c; logs decision creation, status changes, approver assignments - Create record-triggered flow [FLOW_LOG_APPROVAL_ACTIONS] that fires when Compliance_Approval_History__c is created; logs approval with Approval History record details - Create record-triggered flow [FLOW_LOG_RISK_CHANGES] that fires on all changes to Compliance_Risk__c; logs risk creation, status changes, owner changes - Create record-triggered flow [FLOW_LOG_ACTION_ITEM_CHANGES] that fires on all changes to Compliance_Action_Item__c; logs action item creation, status updates, completions - Create record-triggered flow [FLOW_LOG_COMMITTEE_CHANGES] that fires on changes to Compliance_Governance_Committee__c; logs member additions/removals, status changes - Create flow [FLOW_LOG_DATA_ACCESS] invoked by process to monitor report runs and data exports; logs access events to Compliance_Audit_Log__c Access & Permissions: - Create permission set [PERMISSION_SET_AUDIT_VIEWER] allowing read-only access to Compliance_Audit_Log__c - Create permission set [PERMISSION_SET_AUDIT_ADMIN] allowing full CRUD on Compliance_Audit_Log__c and ability to purge logs per retention policy - Restrict access to Compliance_Audit_Log__c by role - ensure only [AUDIT_ROLE] and [COMPLIANCE_ADMIN_ROLE] can access Reports & Dashboards: - Create report [AUDIT_TRAIL_REPORT]: Compliance_Audit_Log__c showing Record_Type, Record_Name, Action, Field_Name, Old_Value, New_Value, User_Name, Change_DateTime, sorted by Change_DateTime descending - Create report [COMPLIANCE_AUDIT_REPORT]: Compliance_Audit_Log__c with filters by date range, user, record type, action type; enables compliance verification and forensic analysis - Create report [DATA_ACCESS_LOG_REPORT]: Compliance_Audit_Log__c filtered to Access_Type = 'Export' or 'Download', showing user, record accessed, timestamp | P17: {=IFERROR(XLOOKUP(D17, '2_Capability_Map'!$C$2:$C$200, '2_Capability_Map'!$M$2:$M$200, "Active"), "Active")} -> Active
A18: GEN-P1C2.7.2-M3-01 | B18: gen_stories_v1 | C18: gen_stories_export.xlsx row for GEN-P1C2.7.2-M3-01 | D18: P1C2.7.2 | E18: Compliance Governance | F18: P1C2.7.2.UC4, P1C2.7.2.UC5 | H18: HIGH | I18: As a Compliance Manager, I want to create a real-time compliance governance dashboard so that leadership can monitor compliance status, key metrics, and committee effectiveness at a glance. | J18: Moving to M3 maturity, the organization gains visibility into compliance governance through analytics dashboards. This story implements a CRM Analytics dashboard that consolidates compliance metrics across all governance objects (committees, policies, decisions, risks, action items). The dashboard provides leadership with KPIs such as compliance decision cycle time, policy approval status, open risk count, action item completion rate, and committee meeting frequency, enabling data-driven governance. | K18: AC1: Given compliance governance data exists in Salesforce, When a [PROFILE_LEADERSHIP] user views the [COMPLIANCE_GOVERNANCE_DASHBOARD], Then they see KPI tiles showing: 'Active Committees', 'Approved Policies', 'Open Risks', 'Overdue Actions', and 'Average Decision Cycle Time'. AC2: Given the dashboard displays policy metrics, When a user views the policy section, Then they see a breakdown of policies by status (Draft, Under Review, Approved, Superseded) and a chart showing policy renewal aging. AC3: Given the dashboard displays risk metrics, When a user views the risk section, Then they see active risks grouped by rating (Critical, High, Medium, Low) and a trend chart showing risk count over the past 12 months. AC4: Given the dashboard displays decision metrics, When a user views the decision section, Then they see pending decisions by type, average approval time by decision type, and overdue decisions highlighted in red. AC5: Given a committee's effectiveness is tracked, When a user views the committee section, Then they see metrics such as meeting frequency compliance, attendance rate, action item closure rate, and average action item completion time. AC6: Given the dashboard displays action item metrics, When a user views the action item section, Then they see counts by status, overdue items flagged, and average days to completion trending over time. AC7: Given the dashboard is accessed by different users, When a [PROFILE_COMPLIANCE_OFFICER] user views the dashboard, Then they see all metrics; when a committee member views it, Then they see only metrics relevant to their assigned committee. | L18: Overview: This story implements a CRM Analytics dashboard in Salesforce that consolidates compliance governance metrics across all governance objects. The dashboard uses SAQL queries and Einstein Discover to surface KPIs, trends, and status indicators that enable compliance leadership to monitor governance effectiveness in real-time. The solution leverages data ingestion from Salesforce objects (policies, decisions, risks, action items, committees) into the [DATASET_NAME] dataset, with role-based access control to ensure appropriate visibility. Object & Field Setup: - No new objects required; uses existing Compliance_Policy__c, Compliance_Decision__c, Compliance_Risk__c, Compliance_Action_Item__c, Compliance_Governance_Committee__c - Ensure all objects have required fields for metric calculations: Status, Owner, Created_Date, Due_Date, Completion_Date Automation: - No changes to automation; existing M1/M2 flows continue to populate objects CRM Analytics Configuration: - Create analytics dataset [DATASET_NAME] with tables: - Policies: sourced from Compliance_Policy__c with fields: Policy_ID, Policy_Name, Status, Policy_Type, Created_Date, Effective_From, Effective_To, Approved_Date, Owner - Decisions: sourced from Compliance_Decision__c with fields: Decision_ID, Decision_Name, Decision_Type, Status, Created_Date, Due_Date, Initiated_By, Current_Approver_User - Risks: sourced from Compliance_Risk__c with fields: Risk_ID, Risk_Name, Status, Risk_Category, Initial_Rating, Current_Rating, Owner, Created_Date, Mitigation_Date, Closed_Date - Action_Items: sourced from Compliance_Action_Item__c with fields: Item_ID, Title, Status, Owner, Created_Date, Due_Date, Completion_Date, Priority - Committees: sourced from Compliance_Governance_Committee__c with fields: Committee_ID, Committee_Name, Chair, Active_Members_Count, Last_Meeting_Date, Next_Meeting_Date - Create dashboards in CRM Analytics: - [COMPLIANCE_GOVERNANCE_DASHBOARD]: - KPI tile: Count of Active_Committees__c - KPI tile: Count of Approved Policies (Status = 'Approved') - KPI tile: Count of Open Risks (Status != 'Closed') - KPI tile: Count of Overdue Action Items (Status = 'Overdue') - KPI tile: Average Decision Cycle Time (calculated as Due_Date - Created_Date) - Gauge: Policy Renewal Compliance (% of policies within review window) - Bar chart: Risks by Category - Trend line: Risk Count trend (past 12 months) - Table: Pending Decisions (Decision_Name, Decision_Type, Days Pending, Current_Approver) - Gauge: Average Decision Approval Time by Decision_Type - Bar chart: Action Items by Status - Trend line: Action Item Completion Rate (over rolling 12 months) - Table: Overdue Actions (Action Title, Owner, Days Overdue) - Committee: Meeting Frequency Compliance, Attendance Rate, Action Item Closure Rate - Create SAQL lens [RISK_TREND_LENS]: analyzes risk trends, identifies spikes, compares to prior periods - Create SAQL lens [DECISION_VELOCITY_LENS]: analyzes decision approval times, identifies bottlenecks - Create SAQL lens [ACTION_ITEM_EFFECTIVENESS_LENS]: analyzes action item completion rates by owner/department Access & Permissions: - Create [DASHBOARD_VIEWER_PERMISSION] allowing users to view [COMPLIANCE_GOVERNANCE_DASHBOARD] - Use dashboard filters to show users only data relevant to their role: - [PROFILE_LEADERSHIP]: see all metrics - [PROFILE_COMPLIANCE_OFFICER]: see all metrics - [PROFILE_COMMITTEE_MEMBER]: see only metrics for assigned committee - [PROFILE_BUSINESS_UNIT_HEAD]: see only metrics for their business unit | P18: {=IFERROR(XLOOKUP(D18, '2_Capability_Map'!$C$2:$C$200, '2_Capability_Map'!$M$2:$M$200, "Active"), "Active")} -> Active
A19: GEN-P1C2.7.2-M3-02 | B19: gen_stories_v1 | C19: gen_stories_export.xlsx row for GEN-P1C2.7.2-M3-02 | D19: P1C2.7.2 | E19: Compliance Governance | F19: P1C2.7.2.UC4, P1C2.7.2.UC1 | G19: OmniStudio, OmniScript | H19: HIGH | I19: As a Risk Manager, I want to provide a self-service compliance risk assessment capability so that business unit heads and process owners can identify and report compliance risks without requiring compliance team involvement. | J19: M3 maturity adds digital self-service experiences. This story implements an OmniScript-based risk identification portal that enables business unit managers to identify potential compliance risks through a guided questionnaire. The portal assesses risk information, severity, and control gaps, creating Compliance_Risk__c records that automatically route to the Risk Officer for review and incorporation into the risk register. | K19: AC1: Given a business unit manager needs to report a compliance risk, When they access [RISK_ASSESSMENT_OMNI_SCRIPT] from the portal, Then they see a guided questionnaire with questions about risk description, category, regulatory reference, current controls, and impact. AC2: Given the manager completes the risk questionnaire, When they click 'Submit Risk Assessment', Then the system creates a Compliance_Risk__c record with Status = 'Submitted for Review', auto-populates fields from the questionnaire responses, and assigns it to the Risk Officer. AC3: Given a risk assessment is submitted, When the Risk Officer reviews the assessment, Then they can approve to add it to the risk register, request additional information, or reject it; the system notifies the submitter of the outcome. AC4: Given the risk assessment questionnaire is displayed, When the manager selects a Risk_Category__c, Then the questionnaire dynamically displays category-specific questions (e.g., regulatory references for Regulatory category). AC5: Given a risk assessment is approved and added to the risk register, When the Risk Officer approves it, Then the system links it to the original submitted assessment and notifies the submitter that their risk is being tracked. AC6: Given the risk assessment portal is accessed, When users with [PROFILE_BUSINESS_UNIT_HEAD] log in, Then they see only the assessment submission portal; when [PROFILE_COMPLIANCE_OFFICER] users log in, Then they see both submission and review capabilities. AC7: Given a manager has submitted a risk assessment, When they return to the portal later, Then they can view the status of their submitted assessments and any feedback from the Risk Officer. | L19: Overview: This story implements a self-service risk identification portal using OmniStudio (OmniScript) that enables business unit managers to identify and report compliance risks without direct compliance team involvement. The solution captures risk information through a guided questionnaire, creates Compliance_Risk__c records, and routes them to the Risk Officer for review. This democratizes risk identification, improves risk visibility, and reduces manual data entry by the compliance team. OmniStudio Configuration: - Create OmniScript [RISK_ASSESSMENT_OMNI_SCRIPT] with the following steps: - Step 1: Risk Identification - Input: Risk_Name__c (text input, required) - Input: Risk_Description__c (long text area, required) - Input: Risk_Category__c (picklist: Regulatory, Operational, Reputational, Control, Other) - Conditional: Based on Risk_Category__c, display category-specific follow-up questions - Step 2: Risk Severity & Controls - Input: Initial_Risk_Rating__c (picklist: Critical, High, Medium, Low, based on questionnaire scoring) - Input: Current_Controls__c (text area describing existing controls) - Input: Control_Effectiveness__c (picklist: Strong, Adequate, Weak, Non-existent) - Calculated: Auto-score Initial_Risk_Rating__c based on impact and likelihood questions - Step 3: Regulatory Reference (conditional on Risk_Category__c = 'Regulatory') - Input: Regulatory_Reference__c (picklist or lookup to regulatory requirements) - Input: Compliance_Deadline__c (date) - Step 4: Review & Submit - Display: Summary of risk information for review - Action: Submit Risk Assessment button - Use DataRaptor [DATARAPTORSAVE_RISK_ASSESSMENT] to extract OmniScript input and create Compliance_Risk__c record - Use DataRaptor [DATARAPTORREAD_RISK_CATEGORIES] to populate Risk_Category__c picklist and category-specific questions - Create Integration Procedure [INTEGRATION_PROC_SUBMIT_RISK] to call DataRaptor save and return confirmation to OmniScript Automation: - Create record-triggered flow [FLOW_RISK_ASSESSMENT_NOTIFICATION] that fires when Compliance_Risk__c is created with source from OmniScript; sends notification to Risk Officer - Create record-triggered flow [FLOW_RISK_STATUS_UPDATE_NOTIFICATION] that fires when Risk_Officer approves/rejects submitted risk; notifies the original submitter Access & Permissions: - Create permission set [PERMISSION_SET_RISK_SUBMITTER] allowing [PROFILE_BUSINESS_UNIT_HEAD] to access and submit risk assessments via OmniScript - Create permission set [PERMISSION_SET_RISK_REVIEWER] allowing [PROFILE_RISK_OFFICER] to review and approve/reject submitted risk assessments - Use Experience Cloud page to host the OmniScript portal, restricting access to appropriate roles Object & Field Setup: - Add field to Compliance_Risk__c: Source_Assessment__c (lookup to a custom assessment object or text field indicating 'OmniScript Submission') - Add field to Compliance_Risk__c: Submitted_By_User__c (lookup to User, auto-filled on OmniScript submission) - Add field to Compliance_Risk__c: Submission_Date__c (date, auto-filled) | P19: {=IFERROR(XLOOKUP(D19, '2_Capability_Map'!$C$2:$C$200, '2_Capability_Map'!$M$2:$M$200, "Active"), "Active")} -> Active
A20: GEN-P1C2.7.2-M3-03 | B20: gen_stories_v1 | C20: gen_stories_export.xlsx row for GEN-P1C2.7.2-M3-03 | D20: P1C2.7.2 | E20: Compliance Governance | F20: P1C2.7.2.UC4, P1C2.7.2.UC5 | H20: HIGH | I20: As a Compliance Manager, I want to generate automated compliance status reports and metrics reports so that I can provide regular updates to leadership on compliance governance progress without manual report creation. | J20: M3 maturity enables automated reporting through CRM Analytics. This story creates a suite of compliance reports and dashboards that are automatically generated on a scheduled basis and distributed to stakeholders. Reports cover policy compliance status, decision approval metrics, risk register status, action item progress, and committee meeting effectiveness. | K20: AC1: Given compliance governance data is maintained in Salesforce, When the scheduled report job runs (e.g., weekly or monthly), Then the system generates [COMPLIANCE_STATUS_REPORT] and distributes it to [STAKEHOLDER_LIST] via email. AC2: Given the compliance status report is generated, When leadership views the report, Then it shows: policies by status, overdue policy reviews, decision approval cycle times, open risk count by rating, overdue action items, and committee meeting compliance. AC3: Given a compliance officer wants to generate a custom report, When they access the [REPORT_BUILDER], Then they can select metrics, filters, and date ranges; the system generates and exports the report in PDF or Excel format. AC4: Given risk status is changing over time, When the [RISK_TREND_REPORT] is generated, Then it shows: risk count trend (over 12 months), risks by category, closed vs. open risks, average time to remediation. AC5: Given action items are tracked, When the [ACTION_ITEM_PERFORMANCE_REPORT] is generated, Then it shows: completion rate by owner, average days to completion, overdue rate, items by status. AC6: Given committee meetings occur regularly, When the [COMMITTEE_EFFECTIVENESS_REPORT] is generated, Then it shows: meeting frequency compliance, attendance rates, action item closure rates from meetings, meeting duration. AC7: Given a compliance officer requests a report snapshot, When they click 'Generate & Download', Then the system creates and downloads a PDF or Excel file with current date and time stamped. | L20: Overview: This story implements a suite of automated compliance reports using CRM Analytics and Salesforce reporting capabilities. The solution creates scheduled reports that aggregate compliance governance metrics, are distributed to stakeholders on a regular cadence, and can be run on-demand by compliance staff. Reports leverage the compliance datasets created in the M3 dashboard story and provide executive-level and detailed operational views of compliance governance status. CRM Analytics & Reporting Configuration: - Create scheduled report job [JOB_WEEKLY_COMPLIANCE_STATUS] that runs weekly (e.g., Monday at 8:00 AM): - Report type: [COMPLIANCE_STATUS_REPORT] (custom analytics dashboard or list view report) - Metrics: Policy count by status, overdue policy review count, decision approval cycle time (avg/max), open risk count by rating, overdue action items, committee meeting compliance % - Output: PDF or Excel, distributed to [STAKEHOLDER_DISTRIBUTION_LIST] - Create scheduled report job [JOB_MONTHLY_RISK_REPORT] that runs monthly (e.g., 1st of month at 8:00 AM): - Report type: [RISK_TREND_REPORT] - Metrics: Risk count trend (12-month), risks by category and rating, closed vs. open, average time to remediation, high-risk items requiring escalation - Output: PDF, distributed to [STAKEHOLDER_DISTRIBUTION_LIST] - Create report [COMPLIANCE_STATUS_REPORT]: List view report or CRM Analytics dashboard showing: - Policies: Count by Status (Draft, Under Review, Approved, Superseded), Overdue Policy Reviews count - Decisions: Average Days to Approve by Decision_Type, Pending Decisions count, Overdue Approvals - Risks: Count by Risk_Rating, Open Risk count, Risks by Category, Average Days to Mitigation - Action Items: % Complete, Overdue count, Average Days to Completion - Committees: Meeting Compliance % (actual vs. planned frequency), Next scheduled meetings - Create report [RISK_TREND_REPORT]: Trend analytics showing: - Risk count trend (past 12 months) with comparison to prior year - Risks by Category (bar chart) - Closed vs. Open risks (pie chart) - Average time to closure (histogram) - Waterfall: Risks opened, closed, remediated (over time period) - Create report [ACTION_ITEM_PERFORMANCE_REPORT]: - Completion % by Owner - Average days to completion by Priority - Overdue count by Owner - Items by Status distribution - Trend: Completion rate over rolling 12 months - Create report [COMMITTEE_EFFECTIVENESS_REPORT]: - Meeting Frequency Compliance % (actual meetings vs. charter requirement) - Attendance Rate % (avg attendance / expected) - Action Item Closure Rate % (items from meetings that closed on time) - Average Meeting Duration vs. planned - Decision Velocity (avg time from committee assignment to approval) - Create report builder configuration [REPORT_BUILDER] in Salesforce allowing compliance officers to: - Select source object (Policies, Decisions, Risks, Action Items, Committees) - Select metrics/fields to include - Filter by date range, status, owner, category - Group by selected dimension - Export to PDF or Excel Automation: - Create scheduled flow [FLOW_GENERATE_WEEKLY_REPORT] that runs weekly; uses Report API to generate report, converts to PDF, and distributes via email using email alert - Alternatively, use Salesforce scheduler to run scheduled report export and email distribution Access & Permissions: - Create permission set [PERMISSION_SET_REPORT_VIEWER] allowing read-only access to compliance reports - Create permission set [PERMISSION_SET_REPORT_BUILDER] allowing compliance officers to create custom reports using report builder | P20: {=IFERROR(XLOOKUP(D20, '2_Capability_Map'!$C$2:$C$200, '2_Capability_Map'!$M$2:$M$200, "Active"), "Active")} -> Active
A21: GEN-P1C2.7.2-M3-04 | B21: gen_stories_v1 | C21: gen_stories_export.xlsx row for GEN-P1C2.7.2-M3-04 | D21: P1C2.7.2 | E21: Compliance Governance | F21: P1C2.7.2.UC4, P1C2.7.2.UC5 | G21: OmniScript | H21: HIGH | I21: As a Compliance Officer, I want to provide a mobile-friendly compliance task management experience so that committee members and action item owners can update status and collaborate from mobile devices. | J21: M3 maturity adds mobile and self-service experiences. This story creates a mobile-optimized experience using OmniScript and Salesforce mobile app customization that enables committee members and action item owners to view assigned tasks, update status, add comments, and upload evidence from mobile devices. This improves accessibility and task completion rates. | K21: AC1: Given a committee member is assigned an action item, When they access the mobile app or portal, Then they see a 'My Tasks' section showing all assigned compliance action items with due date, status, and priority. AC2: Given an action item owner needs to update status, When they open the action item in the mobile app, Then they can change Status__c, add completion comments, and upload supporting evidence without needing a desktop. AC3: Given an action item requires stakeholder approval, When the owner submits for completion, Then the system sends a notification to the approver via mobile notification (if available) or email. AC4: Given the mobile experience is displayed, When a user accesses [COMPLIANCE_MOBILE_PAGE_LAYOUT], Then it is optimized for small screens, shows key fields prominently, and minimizes scrolling and input complexity. AC5: Given a user filters their tasks, When they select filters (e.g., 'High Priority', 'Overdue', 'All Items'), Then the mobile view updates to show only matching items and sorts by due date. AC6: Given an action item is updated on mobile, When the update is saved, Then the system updates the Salesforce record in real-time and notifies any stakeholders configured for notification. AC7: Given a committee member is offline, When they access their task list, Then the mobile app displays cached data from the last sync, and updates sync when connectivity is restored. | L21: Overview: This story implements mobile-friendly compliance task management using Salesforce mobile app customization and OmniScript. The solution creates a mobile page layout for Compliance_Action_Item__c and an OmniScript for task updates that enable users to view and update action items from mobile devices with minimal friction. This improves accessibility, enables faster task completion, and enhances user engagement with compliance governance processes. Object & Field Setup: - Add field to Compliance_Action_Item__c: Mobile_Last_Sync__c (date/time, auto-filled on mobile access) - Ensure all key fields (Status, Completion_Comment, Assigned_To, Due_Date, Priority) are mobile-accessible OmniScript Configuration: - Create OmniScript [MOBILE_ACTION_ITEM_UPDATE] for mobile task updates: - Step 1: Task Details - Display: Action_Title__c, Due_Date__c, Status__c, Priority__c (read-only) - Display: Days Until Due (formula field) - Step 2: Status Update - Input: Status__c (picklist: Not Started, In Progress, Complete, On Hold) - Conditional: If Status__c = 'Complete', display additional fields: - Input: Completion_Date__c (auto-filled = TODAY()) - Input: Completion_Comment__c (long text area, required if Complete) - Input: Supporting_Evidence__c (file upload, optional) - Step 3: Stakeholder Notifications - Checkbox: Notify_On_Update__c (auto-checked if configured) - Display: Email will be sent to [configured stakeholders] - Step 4: Submit - Action: Submit button - Use DataRaptor [DATARAPTORSAVE_MOBILE_ACTION] to save OmniScript input back to Compliance_Action_Item__c - Use Integration Procedure [INTEGRATION_PROC_MOBILE_ACTION_SAVE] to call DataRaptor and trigger notifications Mobile Configuration: - Create custom [PAGE_LAYOUT_MOBILE_ACTION_ITEM] for Salesforce mobile app: - Section 1: Task Summary (Action_Title, Due_Date, Days_Until_Due, Priority) - Section 2: Status (Status__c with mobile-friendly picklist, large buttons for common actions like 'Mark Complete') - Section 3: Comments (Completion_Comment__c with large text input) - Section 4: Evidence (File upload field for supporting documents) - Section 5: Related Risk/Committee (link to parent record) - Action buttons: 'Update Status', 'Add Comment', 'Upload Evidence', 'Submit for Review' - Configure Salesforce mobile app settings to show Compliance_Action_Item__c list in 'My Tasks' section Automation: - Create record-triggered flow [FLOW_NOTIFY_ON_MOBILE_UPDATE] that fires when Compliance_Action_Item__c Status__c is updated from mobile; sends notification to configured stakeholders - Create record-triggered flow [FLOW_LOG_MOBILE_SYNC] that fires on mobile access; updates Mobile_Last_Sync__c timestamp for analytics Access & Permissions: - Create permission set [PERMISSION_SET_MOBILE_USER] allowing read/write access to assigned Compliance_Action_Item__c records via mobile - Use role hierarchy to ensure users can only see assigned tasks | P21: {=IFERROR(XLOOKUP(D21, '2_Capability_Map'!$C$2:$C$200, '2_Capability_Map'!$M$2:$M$200, "Active"), "Active")} -> Active
A22: GEN-P1C2.7.2-M4M5-01 | B22: gen_stories_v1 | C22: gen_stories_export.xlsx row for GEN-P1C2.7.2-M4M5-01 | D22: P1C2.7.2 | E22: Compliance Governance | F22: P1C2.7.2.UC4, P1C2.7.2.UC2 | G22: AI-Generated Insights | H22: HIGH | I22: As a Chief Compliance Officer, I want to implement AI-powered compliance risk prediction and anomaly detection so that the organization can proactively identify emerging compliance risks before they materialize into violations or audit findings. | J22: M4/M5 maturity adds AI-augmented decision support through Agentforce and Data Cloud. This story implements Agentforce agents that analyze compliance data (policies, decisions, risks, audit findings, regulatory changes) to identify patterns, predict emerging risks, and detect anomalies in compliance governance activities. The AI model learns from historical compliance incidents and recommends preventive actions. | K22: AC1: Given compliance data is ingested into Data Cloud, When the AI risk prediction model runs (e.g., weekly), Then it analyzes compliance_risk, audit_findings, and regulatory_change data to identify patterns and generate risk predictions. AC2: Given compliance patterns are analyzed, When the AI model identifies a new risk pattern, Then it creates a predicted Compliance_Risk__c record with Risk_Category__c, Predicted_Impact__c, Confidence_Score__c, and recommended preventive actions. AC3: Given emerging risks are predicted, When a [PROFILE_CCO] user views the [AI_RISK_DASHBOARD], Then they see predicted risks ranked by confidence score and impact, with recommendations for preventive actions. AC4: Given an anomaly is detected in compliance governance, When the AI model identifies unusual approval patterns (e.g., rapid approvals bypassing standard review), Then it flags the anomaly and notifies the Compliance Officer for investigation. AC5: Given the AI risk prediction is displayed, When a user clicks on a predicted risk, Then they see the contributing factors, historical precedents, regulatory references, and recommended remediation actions. AC6: Given the organization wants to validate AI predictions, When a compliance officer reviews and approves an AI-predicted risk, Then the system logs the feedback, and the AI model incorporates it into future predictions to improve accuracy. AC7: Given the AI model is running continuously, When patterns in compliance governance change, Then the model automatically retrains and updates predictions, providing adaptive risk management insights. | L22: Overview: This story implements AI-powered compliance risk prediction and anomaly detection using Agentforce and Data Cloud. The solution ingests compliance governance data from Salesforce objects into Data Cloud, applies machine learning models to detect patterns and predict emerging risks, and presents findings to compliance leadership via a specialized dashboard. The AI learns from historical compliance incidents and user feedback to continuously improve prediction accuracy and provide adaptive compliance insights. Data Cloud Configuration: - Create data ingestion flows to stream Compliance_Risk__c, Compliance_Decision__c, Compliance_Policy__c, Compliance_Action_Item__c, [AUDIT_FINDING_OBJECT], and [REGULATORY_CHANGE_OBJECT] to Data Cloud - Create calculated insights [INSIGHT_RISK_PATTERN_ANALYSIS] that: - Aggregates risks by category, rating, owner, and outcome - Calculates risk metrics: open risk count, average time to closure, remediation effectiveness % - Identifies correlations between risk categories and regulatory requirements - Create calculated insights [INSIGHT_DECISION_ANOMALY_DETECTION] that: - Monitors decision approval patterns: approval time by decision type, approver consistency, bypass incidents - Detects anomalies: decisions approved by non-standard approvers, unusual speed deviations - Create data lake [DATA_LAKE_COMPLIANCE] to store ingested compliance data with retention policy Agentforce Configuration: - Create Agentforce agent [AGENT_COMPLIANCE_RISK_PREDICTOR] with the following capabilities: - Input: Request compliance risk prediction or anomaly analysis - Tool 1: Query Data Cloud calculated insights for historical risk patterns - Tool 2: Analyze current compliance state (open risks, recent decisions, policy changes) - Tool 3: Compare current patterns to historical baselines to detect anomalies - Tool 4: Generate predicted risk records in Salesforce Compliance_Risk__c with Predicted_Impact__c and Confidence_Score__c - Output: Risk predictions with contributing factors, historical precedents, and recommendations - Create Agentforce agent [AGENT_COMPLIANCE_GOVERNANCE_MONITOR] with capabilities: - Monitor compliance decision flows for anomalies - Detect approval chain bypasses or unusual delegations - Alert on policy review overdue dates and regulatory change deadlines - Escalate high-risk anomalies to Compliance Officer - Use Prompt Builder [PROMPT_TEMPLATE_RISK_PREDICTION] to define AI behavior: - Instructions: Analyze compliance data to identify emerging risks, classify by likelihood and impact, provide preventive recommendations - Context: Historical compliance incidents, regulatory requirements, control frameworks - Examples: Sample risk scenarios and recommended actions Automation: - Create scheduled flow [FLOW_RUN_AI_RISK_PREDICTION] that runs weekly; invokes Agentforce agent to generate risk predictions and creates predicted Compliance_Risk__c records - Create scheduled flow [FLOW_RUN_ANOMALY_DETECTION] that runs daily; invokes Agentforce agent to detect compliance governance anomalies and notifies Compliance Officer - Create record-triggered flow [FLOW_LOG_PREDICTION_FEEDBACK] that fires when user validates or corrects AI prediction; logs feedback to improve model accuracy Access & Permissions: - Create permission set [PERMISSION_SET_AI_INSIGHTS_VIEWER] allowing [PROFILE_CCO] and [PROFILE_COMPLIANCE_OFFICER] to view and interact with AI-generated insights - Create permission set [PERMISSION_SET_AI_FEEDBACK_PROVIDER] allowing compliance officers to provide feedback on AI predictions to improve model Reports & Dashboards: - Create dashboard [AI_RISK_DASHBOARD] with components: - Table: Predicted Risks ranked by Confidence_Score and Predicted_Impact - Gauge: Model Accuracy % (based on user validation feedback) - Trend: Emerging risk count trend (predicted vs. actual) - Anomaly alerts: Flagged governance process anomalies - Recommendation engine: Prioritized preventive actions | P22: {=IFERROR(XLOOKUP(D22, '2_Capability_Map'!$C$2:$C$200, '2_Capability_Map'!$M$2:$M$200, "Active"), "Active")} -> Active
A23: GEN-P1C2.7.2-M4M5-02 | B23: gen_stories_v1 | C23: gen_stories_export.xlsx row for GEN-P1C2.7.2-M4M5-02 | D23: P1C2.7.2 | E23: Compliance Governance | F23: P1C2.7.2.UC4, P1C2.7.2.UC2 | H23: HIGH | I23: As a Risk Officer, I want to implement real-time compliance governance monitoring and intelligent alerting so that the organization can respond immediately to compliance governance issues and prevent audit findings. | J23: M4/M5 maturity adds real-time monitoring and predictive governance insights. This story implements Data Cloud-based real-time monitoring of compliance governance activities, with Agentforce-powered intelligent alerting that escalates issues based on risk severity and regulatory context. The system monitors policy compliance, decision approvals, risk status, and action item progress in real-time and proactively alerts when governance is at risk. | K23: AC1: Given compliance governance records are created and updated in Salesforce, When Data Cloud ingests real-time updates, Then the monitoring system detects changes and evaluates them against governance rules and risk thresholds. AC2: Given a policy due for renewal is identified, When the current date exceeds 30 days before Effective_To__c, Then the system generates a priority alert to the Policy_Owner__c and Risk Officer suggesting renewal review initiation. AC3: Given a decision approval is pending beyond the expected cycle time, When the decision has been pending approval for longer than the Decision_Type__c SLA, Then the system sends an escalation alert to the Accountable_Role__c and Risk Officer flagging the delay. AC4: Given a high-risk item is open, When the Risk_Rating__c is 'Critical' and Status__c remains 'Identified' for more than [THRESHOLD_DAYS], Then the system escalates the risk to [ESCALATION_OWNER] and notifies committee members. AC5: Given multiple action items are overdue, When overdue items exceed a threshold (e.g., 3 or more items overdue by >7 days), Then the system generates a summary alert to department head and Risk Officer showing action item health and recommendations. AC6: Given an alert is generated, When a user receives the alert, Then it shows alert severity (Critical, High, Medium, Low), context (which record, why flagged), and recommended action. AC7: Given the organization uses Slack or Teams, When a critical compliance governance alert is generated, Then the system posts the alert to [SLACK_CHANNEL_OR_TEAMS_CHANNEL] for immediate visibility. | L23: Overview: This story implements real-time compliance governance monitoring using Data Cloud and Agentforce. The solution continuously ingests compliance data into Data Cloud, monitors governance activities against defined rules and thresholds, and uses Agentforce agents to intelligently analyze events and escalate issues based on risk and regulatory context. Alerts are delivered in real-time to appropriate stakeholders via Salesforce notifications, email, and Slack/Teams integration, enabling immediate response to governance risks. Data Cloud Configuration: - Create streaming data ingestion for Compliance_Policy__c, Compliance_Decision__c, Compliance_Risk__c, Compliance_Action_Item__c with real-time CDC (Change Data Capture) - Create calculated insights [INSIGHT_POLICY_COMPLIANCE_STATUS]: - Identifies policies due for renewal (Effective_From__c + Review_Frequency__c <= TODAY() + 30) - Calculates % of policies compliant with review schedule - Flags policies with Effective_To__c in past (expired) - Create calculated insights [INSIGHT_DECISION_GOVERNANCE_STATUS]: - Identifies decisions pending approval by Decision_Type__c SLA - Calculates approval cycle time by decision type - Flags decisions exceeding SLA thresholds - Create calculated insights [INSIGHT_RISK_ESCALATION_STATUS]: - Identifies Critical/High risks by time in current status - Flags risks exceeding escalation thresholds - Tracks remediation progress against milestones - Create calculated insights [INSIGHT_ACTION_ITEM_HEALTH]: - Identifies overdue action items by owner and department - Calculates overdue rate by owner and category - Flags owners/departments with high overdue rates Agentforce Configuration: - Create Agentforce agent [AGENT_GOVERNANCE_MONITOR] with capabilities: - Monitor real-time Data Cloud calculated insights for governance status - Analyze alerts against risk severity, regulatory context, and escalation rules - Determine appropriate alert recipient and escalation path - Generate intelligent alert messages with context and recommended action - Route alerts via email, Salesforce notification, Slack, or Teams - Use Prompt Builder [PROMPT_TEMPLATE_GOVERNANCE_ALERT] to define AI behavior: - Instructions: Monitor compliance governance in real-time, identify deviations, escalate issues based on severity and context - Rules: Policy review compliance, decision approval SLAs, risk escalation thresholds, action item completion targets - Escalation paths: Route alerts to appropriate owner based on issue type Automation: - Create scheduled flow or Data Cloud Data Trigger [FLOW_REAL_TIME_GOVERNANCE_MONITORING] that: - Runs every 1 hour (or real-time if CDC is available) - Checks Compliance_Policy__c for policies due for renewal (30-day pre-warning) - Checks Compliance_Decision__c for decisions exceeding approval SLA - Checks Compliance_Risk__c for high-risk items exceeding time threshold - Checks Compliance_Action_Item__c for overdue items exceeding threshold - Invokes Agentforce agent to generate alerts for flagged items - Create integration with Slack via [SLACK_CONNECTOR] to post alerts to [SLACK_CHANNEL_COMPLIANCE] - Create integration with Teams via [TEAMS_CONNECTOR] to post alerts to [TEAMS_CHANNEL_COMPLIANCE] - Create Salesforce notification template [NOTIFICATION_GOVERNANCE_ALERT] for in-app alerts Configuration: - Define alert thresholds in [ALERT_CONFIGURATION_OBJECT]: - Policy Review Pre-Warning: 30 days before due date - Decision Approval SLA by Decision_Type (e.g., Policy Approval: 10 days, Control Exception: 5 days) - Risk Escalation: Critical risk in Identified status for >14 days - Action Item Escalation: >3 items overdue by >7 days - Define escalation paths: - Policy overdue: Policy_Owner__c → Risk Officer → Committee Chair - Decision delayed: Current_Approver__c → Accountable_Role__c → Risk Officer - Risk escalated: Owner__c → Risk Officer → Committee Chair → CCO - Action items overdue: Owner__c → Department Head → Risk Officer Access & Permissions: - Create permission set [PERMISSION_SET_GOVERNANCE_MONITOR] allowing [PROFILE_RISK_OFFICER] and [PROFILE_CCO] to view real-time alerts and acknowledgment status | P23: {=IFERROR(XLOOKUP(D23, '2_Capability_Map'!$C$2:$C$200, '2_Capability_Map'!$M$2:$M$200, "Active"), "Active")} -> Active
A24: GEN-P1C2.7.2-M4M5-03 | B24: gen_stories_v1 | C24: gen_stories_export.xlsx row for GEN-P1C2.7.2-M4M5-03 | D24: P1C2.7.2 | E24: Compliance Governance | F24: P1C2.7.2.UC4, P1C2.7.2.UC2 | H24: HIGH | I24: As a Compliance Officer, I want to enable autonomous compliance governance task management via Agentforce so that routine compliance tasks (approvals, notifications, status updates) are handled by AI agents, freeing up staff for strategic compliance work. | J24: M4/M5 maturity enables autonomous task execution through Agentforce. This story implements AI agents that autonomously handle routine compliance governance tasks such as sending routine notifications, updating action item status based on completion evidence, auto-approving low-risk decisions within defined parameters, and escalating items that require human judgment. This improves operational efficiency and allows compliance staff to focus on high-value strategic activities. | K24: AC1: Given an action item is submitted for completion with supporting evidence, When the evidence meets predefined quality criteria (e.g., document quality, completeness), Then an Agentforce agent autonomously reviews the evidence and approves the action item, updating Status__c to 'Complete'. AC2: Given a low-risk decision is submitted for approval, When the decision is classified as low-risk based on Decision_Type__c and historical approvals, Then an Agentforce agent auto-approves the decision within predefined parameters and routes it to the next step without human intervention. AC3: Given action item owners have submitted completions, When scheduled, Then an Agentforce agent sends status update notifications to all stakeholders summarizing completions, new action items, and any escalations requiring attention. AC4: Given compliance governance tasks are being executed autonomously, When a task falls outside predefined approval parameters (e.g., high-risk decision, incomplete evidence), Then the agent escalates the task to the appropriate human approver with detailed analysis. AC5: Given autonomous task approval has occurred, When the agent approves or escalates a task, Then the decision is logged to [AUDIT_LOG_OBJECT] showing agent approval, decision rationale, and timestamp. AC6: Given an autonomous agent is handling approvals, When a user views the decision or action item, Then they can see that approval was autonomous vs. human-approved, with the AI rationale displayed. AC7: Given compliance staff wants to adjust autonomous task parameters, When they access [AUTONOMOUS_TASK_CONFIGURATION], Then they can update approval thresholds, evidence quality criteria, and escalation rules. | L24: Overview: This story implements autonomous compliance governance task management using Agentforce. The solution creates AI agents that handle routine compliance tasks (approvals, notifications, status updates) autonomously within predefined parameters, escalating items that require human judgment. This improves operational efficiency, reduces manual overhead, and enables compliance staff to focus on strategic activities. All autonomous actions are fully audited and reversible. Agentforce Configuration: - Create Agentforce agent [AGENT_ACTION_ITEM_APPROVER] with capabilities: - Input: Action item submission with completion evidence - Tool 1: Analyze completion evidence (document quality, required fields filled, evidence relevance) - Tool 2: Compare against predefined approval criteria (evidence type, documentation completeness, relevant approval rules) - Tool 3: If criteria met: autonomously approve, update Status__c to 'Complete', log to audit trail - Tool 4: If criteria not met: escalate to human approver with detailed feedback - Output: Approval decision with rationale - Create Agentforce agent [AGENT_DECISION_APPROVER] with capabilities: - Input: Compliance decision submitted for approval - Tool 1: Classify decision risk level (low/medium/high) based on Decision_Type__c, impact, and historical approvals - Tool 2: For low-risk decisions: autonomously approve within authority limits, update Status__c, log decision - Tool 3: For medium/high-risk decisions: escalate to appropriate human approver (Accountable_Role__c) - Output: Approval or escalation decision with rationale - Create Agentforce agent [AGENT_GOVERNANCE_NOTIFIER] with capabilities: - Input: Trigger to send periodic status updates - Tool 1: Query Compliance_Action_Item__c and Compliance_Decision__c for recent completions and new items - Tool 2: Generate summary notifications for stakeholders - Tool 3: Send via email, Slack, or Salesforce notification - Output: Status update sent confirmation - Use Prompt Builder [PROMPT_TEMPLATE_AUTONOMOUS_TASK] to define AI behavior: - Instructions: Execute routine compliance tasks autonomously, follow approval criteria, escalate edge cases - Criteria: Decision risk classification, action item evidence quality, approval authority - Escalation rules: When human judgment is required Automation: - Create record-triggered flow [FLOW_AUTONOMOUS_ACTION_REVIEW] that fires when Compliance_Action_Item__c Status__c changes to 'Ready for Approval'; invokes [AGENT_ACTION_ITEM_APPROVER] - Create record-triggered flow [FLOW_AUTONOMOUS_DECISION_REVIEW] that fires when Compliance_Decision__c Status__c changes to 'Under Review'; invokes [AGENT_DECISION_APPROVER] - Create scheduled flow [FLOW_RUN_AUTONOMOUS_NOTIFIER] that runs daily at 9:00 AM; invokes [AGENT_GOVERNANCE_NOTIFIER] - Create record-triggered flow [FLOW_LOG_AUTONOMOUS_ACTION] that fires when autonomous task is completed; creates audit log entry showing agent action, decision, and rationale Configuration: - Create custom object [AUTONOMOUS_TASK_CONFIG_OBJECT]: Autonomous_Task_Configuration__c with fields: - Task_Type__c (picklist: Action Item Approval, Decision Approval, Notification) - Is_Enabled__c (checkbox) - Risk_Level_Threshold__c (picklist: Auto-approve low-risk only, or low/medium) - Evidence_Quality_Criteria__c (long text area, JSON format) - Escalation_Threshold__c (text) - Owner__c (lookup to User) - Last_Modified_Date__c (date/time) - Populate [AUTONOMOUS_TASK_CONFIG_OBJECT] with initial configuration: - Action Item Approval: Auto-approve if evidence quality score >= 80% and all required fields present - Decision Approval: Auto-approve if risk level = Low and amount <= [THRESHOLD_AMOUNT] - Escalate if risk level = Medium/High or exceptions detected Access & Permissions: - Create permission set [PERMISSION_SET_AUTONOMOUS_ADMIN] allowing [PROFILE_COMPLIANCE_ADMIN] to configure autonomous task parameters - Use audit trail to ensure autonomous actions are trackable and reversible Object & Field Setup: - Add field to Compliance_Action_Item__c: Approved_By_Agent__c (checkbox, auto-filled on autonomous approval) - Add field to Compliance_Decision__c: Approved_By_Agent__c (checkbox, auto-filled on autonomous approval) - Add field to [AUDIT_LOG_OBJECT]: Is_Autonomous_Action__c (checkbox, to flag AI-generated actions) - Add field to [AUDIT_LOG_OBJECT]: Agent_Decision_Rationale__c (long text area, to capture AI reasoning) | P24: {=IFERROR(XLOOKUP(D24, '2_Capability_Map'!$C$2:$C$200, '2_Capability_Map'!$M$2:$M$200, "Active"), "Active")} -> Active
A25: GEN-P1C2.7.3-M1M2-01 | B25: gen_stories_v1 | C25: gen_stories_export.xlsx row for GEN-P1C2.7.3-M1M2-01 | D25: P1C2.7.3 | E25: Exam Readiness | F25: P1C2.7.3.UC4, P1C2.7.3.UC2 | H25: HIGH | I25: As a Compliance Manager, I want to establish a centralized data model for tracking exam readiness across regulatory examination types so that the organization can maintain consistent documentation and visibility of exam preparation status. | J25: Exam readiness begins with a structured foundation to track examination types, preparation timelines, responsible parties, and status. This story establishes the core data model using Salesforce custom objects and FSC components to record and organize all exam-related information. This foundation enables consistent tracking, accountability, and reporting across the organization and supports all downstream automation and analytics. | K25: AC1: Given a compliance manager needs to initiate an exam record, When they create a new exam record with type (e.g., OCC, Federal Reserve, State Regulator), examination date, and responsible party, Then the system creates the record with status = 'Not Started' and stores it in [OBJECT_NAME]. AC2: Given an exam is created, When the record is saved, Then related list of exam preparation tasks, findings, and documentation is available on the record detail page. AC3: Given a user with [PROFILE_NAME] permission set, When they navigate to [PAGE_LAYOUT] for an exam record, Then they see all required fields (Exam Type, Examination Date, Responsible Party, Status, Risk Level, Last Reviewed Date) and cannot modify locked fields based on their stage. AC4: Given an exam record has been created, When a compliance officer updates the exam status to 'In Progress' or 'Findings Received', Then a timestamp is automatically recorded and previous status is retained in audit history. AC5: Given multiple examinations exist, When a user filters exam records by examination date range and risk level, Then the system returns matching records and allows sorting by status and due date. AC6: Given an exam is linked to the relationship, When the system processes records, Then findings and remediation actions are associated with the exam parent record for traceability. | L25: Overview: This story establishes the foundational data architecture for exam readiness tracking using Salesforce custom objects and FSC record types. The solution creates [OBJECT_NAME] as the master record type for individual examinations, with related objects for tasks, findings, and documentation. This centralizes exam information in a single source of truth, enabling consistent tracking, reporting, and compliance with internal governance requirements. The design leverages standard Salesforce features and FSC relationship tracking to ensure scalability. Object & Field Setup: - Create custom object [OBJECT_NAME] or use FSC Compliance object with fields: Exam Type (picklist: OCC, Federal Reserve, State Regulator, FDIC, NCUA), Examination Date (date), Responsible Party (lookup to User/Role), Current Status (picklist: Not Started, In Progress, Under Review, Findings Received, Remediation In Progress, Closed), Risk Level (picklist: Low, Medium, High, Critical), Last Reviewed Date (date), Exam Period (text for fiscal/calendar period) - Create related list junction object [EXAM_TASK_OBJECT] with fields: Exam (lookup), Task Description, Responsible Owner, Due Date, Status, Completion Date, Priority - Create related list junction object [EXAM_FINDING_OBJECT] with fields: Exam (lookup), Finding Number, Area/Topic, Severity (picklist: Minor, Major, Critical), Description, Remediation Required (checkbox), Remediation Owner, Target Remediation Date, Actual Remediation Date, Status - Create related list junction object [EXAM_DOCUMENT_OBJECT] with fields: Exam (lookup), Document Name, Document Type (picklist: Audit Trail, Policy, Report, Supporting Evidence), Upload Date, Reviewed (checkbox), Review Date, Reviewer Access & Permissions: - Create [PERMISSION_SET] for Compliance Managers enabling full CRUD on [OBJECT_NAME], [EXAM_TASK_OBJECT], [EXAM_FINDING_OBJECT], [EXAM_DOCUMENT_OBJECT] - Create [PERMISSION_SET] for Business Managers enabling read-only access on related exam records; edit on assigned tasks and findings - Create [PERMISSION_SET] for Executives enabling read-only access to exam status summaries - Create [SHARING_RULE] to share exam records with responsible parties and related business teams based on Exam Type and Responsible Party field Automation: - Create validation rule preventing modification of locked status fields (Closed exams cannot be edited except by Compliance Managers) - Create field-update flow to automatically set Last Reviewed Date when Status is updated - Create record-triggered flow to create audit trail entry when exam record is created or status changes Page Layouts: - Create [PAGE_LAYOUT] for Exam record showing Exam Type, Examination Date, Responsible Party, Status, Risk Level as prominent fields - Add related lists for tasks, findings, and documents below the fold - Create read-only layout variant for Executive viewers | P25: {=IFERROR(XLOOKUP(D25, '2_Capability_Map'!$C$2:$C$200, '2_Capability_Map'!$M$2:$M$200, "Active"), "Active")} -> Active
A26: GEN-P1C2.7.3-M1M2-02 | B26: gen_stories_v1 | C26: gen_stories_export.xlsx row for GEN-P1C2.7.3-M1M2-02 | D26: P1C2.7.3 | E26: Exam Readiness | F26: P1C2.7.3.UC4, P1C2.7.3.UC2 | H26: HIGH | I26: As a Compliance Manager, I want to centralize exam-related documentation so that all required examination materials are organized, version-controlled, and accessible to authorized stakeholders. | J26: Exam preparation requires managing numerous documents-policies, audit trails, reports, evidence packages, and regulatory correspondence. This story establishes a centralized document repository within Salesforce tied to exam records, enabling organized storage, version control, and role-based access. The solution uses Salesforce document management with audit trails to ensure all stakeholders can quickly locate required materials while maintaining compliance with document retention policies. | K26: AC1: Given a compliance officer needs to upload exam documentation, When they navigate to the Exam Documents section and attach a file to an exam record, Then the file is stored with metadata (upload date, uploader, document type, exam reference) in [DOCUMENT_STORAGE]. AC2: Given exam documents exist, When a user filters documents by Exam Type and Document Category (e.g., Audit Trails, Policies, Supporting Evidence), Then results are returned with pagination and sort options. AC3: Given a document is uploaded, When the system checks folder permissions, Then only users with [PERMISSION_SET] for that exam's responsible area can view the document. AC4: Given a document requires version control, When a user uploads a new version of an existing document, Then the previous version is retained with a version number and timestamp, and the current version is marked as 'Active'. AC5: Given an exam document package is prepared, When a compliance manager marks a document as 'Reviewed', Then a review timestamp and reviewer name are recorded, and the document status updates in the Exam record. AC6: Given a user needs to generate a document package for an exam, When they select 'Create Document Package' from the Exam record, Then all linked documents are collected and a summary report is generated with document names, upload dates, and review status. | L26: Overview: This story creates a centralized, role-based document management system for exam materials within Salesforce. Documents are stored in a [DOCUMENT_FOLDER_STRUCTURE] organized by exam type and topic, with metadata capturing upload date, version, reviewer, and review status. The solution leverages Salesforce document management capabilities and folder sharing rules to ensure compliance officers can quickly assemble exam packages while maintaining version history and audit trails. Related list on exam records provides direct access to associated documents. Object & Field Setup: - Use Salesforce ContentDocument and ContentVersion objects to store exam materials; create custom metadata fields in [EXAM_DOCUMENT_OBJECT]: Document Type (picklist: Audit Trail, Policy, Report, Supporting Evidence, Correspondence, Other), Review Status (picklist: Pending Review, Reviewed, Signed Off), Reviewer Name (text), Review Date (date), Version Number (auto-increment) - Create folder structure in [DOCUMENT_FOLDER_STRUCTURE]: /Examinations/[EXAM_TYPE]/[EXAM_YEAR]/[TOPIC_AREA]/ Access & Permissions: - Create [PERMISSION_SET] for Compliance Team with edit access to exam documentation folders - Create [PERMISSION_SET] for Business Unit Managers with read-only access to their exam documents - Create [SHARING_RULE] to share exam document folders with responsible parties based on exam assignment - Lock [DOCUMENT_FOLDER_STRUCTURE] to prevent unauthorized reorganization Automation: - Create record-triggered flow: when exam document is uploaded, capture upload date, uploader, and automatically link to parent exam record - Create validation rule: document uploads to exam folders require Document Type picklist value - Create field-update flow to set Review Status = 'Pending Review' on new document uploads Reports & Dashboards: - Create report [EXAM_DOCUMENTS_REPORT] showing document name, upload date, reviewer, review status, version count grouped by exam - Add filter to show only documents pending review | P26: {=IFERROR(XLOOKUP(D26, '2_Capability_Map'!$C$2:$C$200, '2_Capability_Map'!$M$2:$M$200, "Active"), "Active")} -> Active
A27: GEN-P1C2.7.3-M1M2-03 | B27: gen_stories_v1 | C27: gen_stories_export.xlsx row for GEN-P1C2.7.3-M1M2-03 | D27: P1C2.7.3 | E27: Exam Readiness | F27: P1C2.7.3.UC4, P1C2.7.3.UC2 | H27: HIGH | I27: As a Compliance Manager, I want to assign exam preparation tasks to responsible teams and track completion status so that stakeholders understand their obligations and the organization can monitor exam readiness progress. | J27: Exam preparation involves coordinating activities across multiple departments-data validation, policy reviews, evidence gathering, training coordination. This story creates a task management system where compliance managers assign exam prep activities to responsible parties, set deadlines, and track progress. The solution leverages Salesforce action plans and task objects to ensure clear ownership, accountability, and visibility of exam preparation status throughout the organization. | K27: AC1: Given a compliance manager has identified exam prep activities, When they create exam tasks from the Exam record with Task Description, Responsible Owner, Due Date, and Priority, Then each task is stored in [EXAM_TASK_OBJECT] with status = 'Not Started'. AC2: Given an exam task is assigned to a user, When the system saves the task, Then the Responsible Owner receives a notification (email or in-app) with the task description, due date, and link to the exam record. AC3: Given a task owner has completed an exam task, When they update task status to 'Completed' and save, Then completion date is automatically recorded and the exam preparation progress is updated. AC4: Given tasks are assigned to multiple owners, When a compliance manager views the Exam record, Then a related list shows all tasks with status (Not Started, In Progress, Completed, Overdue), due date, and owner filtered by exam. AC5: Given a task is past its due date, When the system runs daily, Then the task status is automatically updated to 'Overdue' and Responsible Owner receives an escalation notification. AC6: Given an exam has multiple tasks in progress, When a user filters tasks by status, exam type, and due date range, Then a task report is generated showing task backlog, completion rate, and at-risk tasks. AC7: Given an exam task is critical, When the Compliance Manager sets Priority = 'High', Then the task appears in the executive exam readiness dashboard as a focus area. | L27: Overview: This story creates a task management layer for exam preparation activities using Salesforce custom [EXAM_TASK_OBJECT] linked to exam records. Tasks capture description, responsible owner, due date, priority, and status with automatic notifications, escalation, and progress tracking. The design enables granular assignment of exam prep work, clear accountability at the individual level, and real-time visibility of which activities are complete, in-progress, or at-risk. Status changes trigger automation for notifications and exam-level status updates. Object & Field Setup: - [EXAM_TASK_OBJECT] fields: Exam (lookup to [OBJECT_NAME]), Task Description (text), Task Category (picklist: Data Validation, Policy Review, Evidence Gathering, Training, Testing, Reporting, Other), Responsible Owner (lookup to User), Due Date (date), Priority (picklist: Low, Medium, High, Critical), Status (picklist: Not Started, In Progress, Completed, Blocked, Cancelled), Start Date (date), Completion Date (date), Percent Complete (number), Notes (long text) - Create related list on [OBJECT_NAME] to display all associated tasks Automation: - Create record-triggered flow: when [EXAM_TASK_OBJECT] is created, send notification to Responsible Owner with task details and exam link - Create scheduled flow: daily evaluation of tasks with due date before today and status != 'Completed'; update status to 'Overdue' and send escalation to Responsible Owner and Compliance Manager - Create field-update flow: when task status changes to 'Completed', set Completion Date = TODAY() - Create rollup summary field on [OBJECT_NAME]: count of tasks with status = 'Completed' vs. total tasks to calculate Exam Readiness % Complete Access & Permissions: - Create [PERMISSION_SET] for Compliance Managers: full CRUD on [EXAM_TASK_OBJECT] - Create [PERMISSION_SET] for Business Unit Managers: edit tasks assigned to them; read-only on other tasks - Create [PERMISSION_SET] for Task Owners: read and update status on assigned tasks only - Create [SHARING_RULE] to share tasks with task owner and their manager Validation Rules: - Prevent past due dates on task creation - Require Task Description and Responsible Owner before task can be saved - Prevent status change to 'Completed' if Percent Complete < 100 | P27: {=IFERROR(XLOOKUP(D27, '2_Capability_Map'!$C$2:$C$200, '2_Capability_Map'!$M$2:$M$200, "Active"), "Active")} -> Active
A28: GEN-P1C2.7.3-M1M2-04 | B28: gen_stories_v1 | C28: gen_stories_export.xlsx row for GEN-P1C2.7.3-M1M2-04 | D28: P1C2.7.3 | E28: Exam Readiness | F28: P1C2.7.3.UC4, P1C2.7.3.UC2 | H28: HIGH | I28: As an Executive Compliance Officer, I want to generate exam readiness status reports so that leadership understands the organization's preparedness for upcoming examinations and can make informed decisions about resource allocation. | J28: Exam readiness visibility at the executive level requires clear, timely reporting on examination status, progress, and risk areas. This story creates standard reports and dashboards that consolidate exam information, task completion, findings, and remediation status. The solution leverages Salesforce reports to provide compliance leadership with accurate, actionable views of exam preparation across the organization and supports communication with the board and external regulators. | K28: AC1: Given an executive needs to assess exam readiness, When they navigate to [DASHBOARD_NAME], Then they see count of exams by status (Not Started, In Progress, Under Review, Findings Received, Closed), exam timeline (upcoming exams in next 30/60/90 days), and overall readiness percentage. AC2: Given exam preparation involves multiple areas, When a user opens [REPORT_NAME], Then results show exam type, examination date, responsible party, status, number of pending tasks, and critical findings. AC3: Given a task is overdue or exam is approaching, When the dashboard refreshes, Then status is highlighted in yellow (At Risk) or red (Critical) based on days until examination date and task completion rate. AC4: Given an executive wants detail on a specific exam, When they click on an exam record from the report/dashboard, Then the detail page shows exam timeline, task status, findings summary, and document checklist. AC5: Given exam data changes throughout the week, When the [REPORT_NAME] is refreshed, Then data reflects current exam status, task completion, and finding updates within 1 hour of record modification. AC6: Given leadership meets monthly to review compliance status, When they export [REPORT_NAME] to PDF, Then the export includes exam status summary, timeline, risk indicators, and trend analysis (exam readiness trend over last 3 months). AC7: Given a specific exam type requires board reporting, When a user filters [DASHBOARD_NAME] by Exam Type (e.g., Federal Reserve), Then a focused view shows only relevant exams and is ready for board distribution. | L28: Overview: This story creates a suite of reports and dashboards to provide executive visibility into exam readiness status and progress. Using Salesforce Reports, the solution aggregates exam records, tasks, and findings into status views, timeline visualizations, and risk indicators. Reports support filtering by exam type, date range, responsible party, and status. Dashboards provide at-a-glance KPIs (exam count by status, task completion %, findings trend) and drill-down capability to underlying exam records. The design enables leadership to quickly identify at-risk exams and make informed resource decisions. Reports & Dashboards: - Create tabular report [EXAM_STATUS_REPORT]: Exam Type, Examination Date, Responsible Party, Current Status, Risk Level, Task Completion %, Critical Findings Count, Last Updated; filter by date range, status, risk level; group by Exam Type and Status - Create summary report [EXAM_TIMELINE_REPORT]: Examination Date, Days Until Exam, Exam Type, Status, Task Backlog, Overdue Tasks; sorted chronologically; show upcoming exams in next 90 days - Create matrix report [EXAM_FINDINGS_REPORT]: Exam Type vs. Severity (rows vs. columns), count of findings by severity and remediation status; filter by exam date range - Create [DASHBOARD_NAME] with components: * Gauge: Overall Exam Readiness % (completed tasks / total tasks across all active exams) * Bar chart: Exam count by Status (Not Started, In Progress, Under Review, Findings Received, Closed) * Timeline/Gantt visual: Upcoming exams with due dates and current status * Number card: Critical findings (severity = Critical) pending remediation * Number card: Overdue tasks count * Related list component: Last 5 exams updated - Add filter to [DASHBOARD_NAME] for Exam Type, Date Range, Responsible Party enabling dynamic filtering Automation: - Create scheduled flow: daily calculation of exam readiness % based on task completion; update [OBJECT_NAME].Readiness_Percentage field - Create scheduled flow: weekly report distribution to [EMAIL_LIST] with top 5 at-risk exams and action items Access & Permissions: - Share [DASHBOARD_NAME] with [PROFILE_NAME] for Executives and Compliance Managers - Create [PERMISSION_SET] for report access: Compliance Managers and above can view all reports; Business Managers see filtered reports (their exams only) Validation: - Ensure all active exams appear in [EXAM_STATUS_REPORT] - Verify task completion % matches task list on exam record - Validate findings count matches [EXAM_FINDING_OBJECT] records | P28: {=IFERROR(XLOOKUP(D28, '2_Capability_Map'!$C$2:$C$200, '2_Capability_Map'!$M$2:$M$200, "Active"), "Active")} -> Active
A29: GEN-P1C2.7.3-M1M2-05 | B29: gen_stories_v1 | C29: gen_stories_export.xlsx row for GEN-P1C2.7.3-M1M2-05 | D29: P1C2.7.3 | E29: Exam Readiness | F29: P1C2.7.3.UC4, P1C2.7.3.UC5 | H29: HIGH | I29: As a Compliance Manager, I want to systematically record examination findings and track remediation actions so that the organization can demonstrate timely resolution of issues identified by regulators. | J29: Following an examination, regulators communicate findings that must be documented, investigated, and remediated. This story creates a structured process for recording findings by severity level, assigning remediation ownership, tracking action completion, and maintaining audit evidence. The solution ensures findings are not overlooked, remediation timelines are monitored, and the organization maintains a complete record of finding resolution for future examination cycles. | K29: AC1: Given an examination has concluded with findings, When a Compliance Manager creates a finding record with Finding Number, Area/Topic, Severity (Minor/Major/Critical), and detailed Description, Then the finding is stored in [EXAM_FINDING_OBJECT] with status = 'Open'. AC2: Given a finding requires remediation, When the Compliance Manager checks 'Remediation Required', assigns a Remediation Owner, and sets Target Remediation Date, Then the system creates a linked remediation action item and notifies the Remediation Owner. AC3: Given a remediation action is assigned, When the Remediation Owner completes the corrective action and updates finding status to 'In Progress', Then Start Date is recorded and progress tracking begins. AC4: Given a remediation action is in progress, When the deadline approaches (within 14 days), Then an escalation notification is sent to the Remediation Owner and their manager. AC5: Given a remediation is completed, When the Remediation Owner updates status to 'Completed', verifies with evidence (document, policy, training record), and saves, Then Actual Remediation Date is recorded and Compliance Manager is notified for final review. AC6: Given a finding has supporting documentation, When Compliance Manager attaches evidence (policy, audit trail, certification), Then evidence is linked to the finding record with upload date and file name. AC7: Given findings are tracked across exams, When a Compliance Manager filters findings by severity and remediation status, Then a report shows open critical findings, overdue remediation items, and exams with unresolved findings. AC8: Given an exam cycle closes, When findings are marked 'Closed' (remediation complete and verified), Then closure date is recorded and finding is archived for historical reference. | L29: Overview: This story creates a findings management system using [EXAM_FINDING_OBJECT] to document regulatory examination results, assign remediation responsibility, and track resolution. Findings are linked to parent exam records, categorized by severity (Minor/Major/Critical), and tied to specific business areas. The solution assigns clear ownership of remediation, establishes target dates, and monitors progress through completion. Automation escalates overdue items, notifications ensure timely action, and audit trails document the complete resolution history. This approach ensures regulators can see evidence of thorough, timely remediation during follow-up examinations. Object & Field Setup: - [EXAM_FINDING_OBJECT] fields: Exam (lookup to [OBJECT_NAME]), Finding Number (text, unique identifier assigned by regulator), Area/Topic (text, e.g., 'Data Governance', 'Compliance Controls'), Severity (picklist: Minor, Major, Critical), Description (long text), Remediation Required (checkbox), Remediation Owner (lookup to User), Target Remediation Date (date), Actual Remediation Date (date), Status (picklist: Open, In Progress, Completed, Verified, Closed), Notes (long text), Evidence (attachment/file field), Review Date (date), Reviewed By (lookup to User) - Create related list on [OBJECT_NAME] to display findings with status and due date - Create related list on finding record to display supporting documents/evidence Automation: - Create record-triggered flow: when finding is created, populate Finding Number with exam year + sequential counter (e.g., 'EX-2025-001') - Create record-triggered flow: when finding created with Remediation Required = true, send notification to Remediation Owner with finding summary, description, and target date - Create scheduled flow: daily check for findings with Target Remediation Date within 14 days and status != 'Closed'; send escalation to Remediation Owner and Compliance Manager - Create record-triggered flow: when status changes to 'Completed', set Actual Remediation Date = TODAY() and notify Compliance Manager for verification - Create record-triggered flow: when status changes to 'Verified' (Compliance Manager confirmation), set Review Date = TODAY() and Reviewed By = current user Access & Permissions: - Create [PERMISSION_SET] for Compliance Managers: full CRUD on [EXAM_FINDING_OBJECT] - Create [PERMISSION_SET] for Remediation Owners: read-only on assigned findings; edit status and notes on assigned findings only - Create [PERMISSION_SET] for Executives: read-only on all findings - Create [SHARING_RULE] to share findings with remediation owner and their manager Reports & Dashboards: - Create report [FINDINGS_SUMMARY_REPORT]: Exam, Finding Number, Area, Severity, Status, Target Date, Actual Date; grouped by status and severity; filter by severity (show Critical priority) - Create report [REMEDIATION_TRACKING_REPORT]: Finding, Remediation Owner, Days Remaining, Status; sorted by Days Remaining; highlight overdue items Validation Rules: - Require Finding Description, Area, and Severity before save - If Remediation Required = true, require Remediation Owner and Target Remediation Date - Prevent Actual Remediation Date from being earlier than finding creation date - Prevent closing findings with Critical severity without Compliance Manager review | P29: {=IFERROR(XLOOKUP(D29, '2_Capability_Map'!$C$2:$C$200, '2_Capability_Map'!$M$2:$M$200, "Active"), "Active")} -> Active
A30: GEN-P1C2.7.3-M3-01 | B30: gen_stories_v1 | C30: gen_stories_export.xlsx row for GEN-P1C2.7.3-M3-01 | D30: P1C2.7.3 | E30: Exam Readiness | F30: P1C2.7.3.UC1, P1C2.7.3.UC4 | G30: OmniStudio, OmniScript | H30: HIGH | I30: As a Compliance Officer, I want business teams to complete a self-service exam readiness assessment so that compliance can gather comprehensive readiness input without manual interviews and identify gaps early. | J30: Exam readiness assessment requires input from business units about data quality, process compliance, training completion, and system functionality. Rather than compliance conducting one-on-one interviews, this story creates an interactive questionnaire that business managers complete independently. The OmniScript captures structured responses, auto-populates readiness records with findings, and generates a readiness score. This M3 enhancement reduces manual effort and provides real-time visibility into which areas need remediation before the examination. | K30: AC1: Given a business manager needs to assess their area's exam readiness, When they navigate to [OMNI_SCRIPT_NAME] from a dashboard or notification, Then they see a guided questionnaire with 15-20 questions organized by category (Data Quality, Controls, Training, Processes, Technology). AC2: Given a business manager completes the questionnaire, When they select 'Submit', Then responses are validated (all required fields answered) and auto-populate fields on a linked [ASSESSMENT_OBJECT] record: Area, Submission Date, Respondent, Readiness Score, and Response Summary. AC3: Given an assessment reveals gaps (e.g., incomplete training, data quality issues), When responses indicate a gap, Then the system auto-creates remediation action items with owner (area manager), description, and target date (based on exam date). AC4: Given a business manager needs context, When they click a question in [OMNI_SCRIPT_NAME], Then a tooltip or supporting documentation appears explaining what compliance is assessing and why the answer matters. AC5: Given compliance needs to review submissions, When they open [DASHBOARD_NAME], Then they see a list of completed assessments, submission status by area, average readiness score, and areas with the lowest scores highlighted. AC6: Given an assessment is incomplete, When the deadline approaches (14 days before exam), Then the business manager receives an escalation notification and compliance manager is alerted in the dashboard. AC7: Given assessments are submitted, When compliance opens a completed assessment record, Then they see the readiness score, response summary, identified gaps, and can add compliance notes or schedule a follow-up discussion. AC8: Given multiple areas have submitted assessments, When compliance filters [DASHBOARD_NAME] by exam type and submission status, Then they see which areas are exam-ready and which require intensive remediation focus. | L30: Overview: This story creates a self-service exam readiness questionnaire using OmniStudio OmniScript, enabling business managers to independently assess their area's preparedness without compliance interviews. The OmniScript presents 15-20 structured questions organized by functional area (Data Quality, Controls, Training, Processes, Technology), with conditional logic showing follow-up questions based on responses. Upon submission, responses auto-populate a custom Assessment object, calculate a readiness score (% positive responses), and trigger creation of remediation actions for gaps. A supporting dashboard provides compliance with real-time visibility into submission status, area readiness scores, and identified gaps. This approach reduces compliance effort, accelerates readiness assessment, and provides quantifiable input to exam preparation planning. Object & Field Setup: - Create custom object [ASSESSMENT_OBJECT] with fields: Exam (lookup to [OBJECT_NAME]), Business Area (picklist: [CLIENT_ORG] functional areas), Respondent (lookup to User), Submission Date (date), Readiness Score (percentage calculation: positive responses / total questions), Assessment Status (picklist: Draft, Submitted, Under Review, Approved), Compliance Notes (long text), Overall Readiness (text summary based on score tiers: <50% Critical, 50-75% At Risk, 75-90% Ready, >90% Strong) - Create question library table: Questions (ID, Category, Question Text, Question Type, Required, Help Text, Follow-up Logic) OmniStudio Configuration: - Create [OMNI_SCRIPT_NAME] with: * Start screen: Business Area selection (dropdown), Respondent name (auto-populated from current user) * Question blocks organized by category (5 questions each): - Data Quality: data validation processes, completeness checks, reconciliation - Controls: access controls, segregation of duties, audit trails, policy compliance - Training: exam-specific training completion %, coverage by role, certification status - Processes: documented procedures, change management, exception handling - Technology: system testing, backup/recovery, availability, access controls * Conditional logic: if response indicates gap, show follow-up question (e.g., 'When will you complete training?') * DataRaptor write action at submission: save responses to [ASSESSMENT_OBJECT] and create linked remediation action items * Response score calculation: post-submission, display Readiness % to respondent * Submission confirmation: show summary of identified gaps and explain next steps - Add [OMNI_SCRIPT_NAME] to community portal or internal Experience Cloud site for easy access Automation: - Create record-triggered flow: when [ASSESSMENT_OBJECT] is submitted, calculate Readiness Score from response data; auto-create [EXAM_TASK_OBJECT] record for each identified gap with owner = Business Area Manager, due date = exam date - 30 days, task = remediate identified gap - Create scheduled flow: 14 days before exam, identify [ASSESSMENT_OBJECT] records with Readiness Score < 75%; send escalation to Respondent and Compliance Manager - Create record-triggered flow: when assessment is marked 'Approved' by compliance, send confirmation to business area with approved readiness status and any follow-up actions Reports & Dashboards: - Create [DASHBOARD_NAME] component: Scorecard showing average Readiness Score across all areas, with breakdown by area (bar chart) - Add filter: Exam Type, Submission Status enabling real-time tracking - Add related list: Recent assessments with submission date, area, score, and status - Create report [ASSESSMENT_REPORT]: Business Area, Respondent, Submission Date, Readiness Score, Overall Readiness, Gaps Identified; grouped by area; sorted by readiness score Access & Permissions: - Create [PERMISSION_SET] for Business Managers: edit [OMNI_SCRIPT_NAME] (their own submissions only), read-only access to [ASSESSMENT_OBJECT] - Create [PERMISSION_SET] for Compliance Managers: full CRUD on [ASSESSMENT_OBJECT], view all assessments, access [DASHBOARD_NAME] - Share [OMNI_SCRIPT_NAME] via Experience Cloud or internal portal to all business managers Validation Rules: - Require Business Area and Respondent before assessment submission - Require follow-up response if gap is identified (e.g., remediation target date) | P30: {=IFERROR(XLOOKUP(D30, '2_Capability_Map'!$C$2:$C$200, '2_Capability_Map'!$M$2:$M$200, "Active"), "Active")} -> Active
